Workbook

Sheet README
A1: ABBank Business Intelligence System - Master Workbook | B1: ABBank Business Intelligence System - Master Workbook | C1: ABBank Business Intelligence System - Master Workbook | D1: ABBank Business Intelligence System - Master Workbook | E1: ABBank Business Intelligence System - Master Workbook | F1: ABBank Business Intelligence System - Master Workbook | G1: ABBank Business Intelligence System - Master Workbook | H1: ABBank Business Intelligence System - Master Workbook
A3: Mục tiêu | B3: Hệ thống BI bao phủ Vĩ mô → Ngành ngân hàng → ABBank → Treasury → Khuyến nghị hành động.
A4: Cách dùng | B4: Nhập/cập nhật dữ liệu tại các sheet INPUT_*. Các sheet PROC_* và DASH_* tự tổng hợp bằng công thức.
A5: Tần suất | B5: Macro: tháng; Industry: quý; ABBank: tháng; Treasury: ngày/tháng; Scenario: theo giả định quản trị.
A6: Danh mục mẫu | B6: Quy mô danh mục Treasury mặc định 50.000 tỷ VND; vốn Treasury 20.000 tỷ VND.
A7: Lưu ý | B7: Các dữ liệu trong file là dữ liệu mẫu để dựng cấu trúc. Khi triển khai thật cần thay bằng số liệu ABBank/NHNN/GSO/VBMA/peer banks.

Sheet CONFIG
A1: Configuration & Thresholds | B1: Configuration & Thresholds | C1: Configuration & Thresholds | D1: Configuration & Thresholds | E1: Configuration & Thresholds
A3: Parameter | B3: Value | C3: Unit | D3: Meaning | E3: Owner
A4: portfolio_size | B4: 50000 | C4: tỷ VND | D4: Quy mô danh mục Treasury | E4: Treasury
A5: treasury_capital | B5: 20000 | C5: tỷ VND | D5: Vốn Treasury dùng cho risk appetite | E5: Treasury
A6: vnibor_yellow | B6: 4.5 | C6: % | D6: Ngưỡng cảnh báo VNIBOR ON vàng | E6: ALM
A7: vnibor_red | B7: 5.5 | C7: % | D7: Ngưỡng cảnh báo VNIBOR ON đỏ | E7: ALM
A8: fx_yellow | B8: 1.5 | C8: % MoM | D8: Ngưỡng cảnh báo biến động USD/VND vàng | E8: Treasury
A9: fx_red | B9: 3 | C9: % MoM | D9: Ngưỡng cảnh báo biến động USD/VND đỏ | E9: Treasury
A10: ldr_yellow | B10: 85 | C10: % | D10: Ngưỡng LDR vàng | E10: Finance
A11: ldr_red | B11: 90 | C11: % | D11: Ngưỡng LDR đỏ | E11: Finance
A12: npl_yellow | B12: 2.5 | C12: % | D12: Ngưỡng NPL vàng | E12: Risk
A13: npl_red | B13: 3 | C13: % | D13: Ngưỡng NPL đỏ | E13: Risk
A14: stress_limit_yellow | B14: 3 | C14: % capital | D14: Loss/tổng vốn Treasury - vàng | E14: Treasury
A15: stress_limit_red | B15: 5 | C15: % capital | D15: Loss/tổng vốn Treasury - đỏ | E15: Treasury

Sheet SOURCES
A1: Suggested Data Sources | B1: Suggested Data Sources | C1: Suggested Data Sources | D1: Suggested Data Sources
A3: Data area | B3: Primary source | C3: URL | D3: Notes
A4: Macro / monetary policy | B4: State Bank of Vietnam | C4: https://www.sbv.gov.vn | D4: Policy rate, credit, money market commentary
A5: GDP / CPI / trade / retail | B5: General Statistics Office of Vietnam | C5: https://www.nso.gov.vn | D5: Monthly/quarterly macro releases
A6: Bond market / yield curve | B6: Vietnam Bond Market Association | C6: https://vbma.org.vn | D6: Bond yields, market updates
A7: Peer banks | B7: Published financial statements / investor relations | C7: https://www.hnx.vn / https://www.hsx.vn | D7: Quarterly peer benchmarking
A8: ABBank internal | B8: MIS / Finance / Risk / Treasury internal systems | C8: Internal | D8: Replace sample data with governed internal data

Sheet INPUT_MACRO
A1: INPUT_MACRO - Monthly Macro & Market Data | B1: INPUT_MACRO - Monthly Macro & Market Data | C1: INPUT_MACRO - Monthly Macro & Market Data | D1: INPUT_MACRO - Monthly Macro & Market Data | E1: INPUT_MACRO - Monthly Macro & Market Data | F1: INPUT_MACRO - Monthly Macro & Market Data | G1: INPUT_MACRO - Monthly Macro & Market Data | H1: INPUT_MACRO - Monthly Macro & Market Data | I1: INPUT_MACRO - Monthly Macro & Market Data | J1: INPUT_MACRO - Monthly Macro & Market Data | K1: INPUT_MACRO - Monthly Macro & Market Data | L1: INPUT_MACRO - Monthly Macro & Market Data | M1: INPUT_MACRO - Monthly Macro & Market Data | N1: INPUT_MACRO - Monthly Macro & Market Data | O1: INPUT_MACRO - Monthly Macro & Market Data | P1: INPUT_MACRO - Monthly Macro & Market Data
A3: date | B3: gdp_growth | C3: cpi | D3: core_cpi | E3: industrial_production | F3: retail_sales | G3: export_growth | H3: import_growth | I3: usd_vnd | J3: policy_rate | K3: omo | L3: tin_phieu | M3: vnibor_on | N3: vnibor_1w | O3: credit_growth | P3: deposit_growth
A4: 44227 | B4: 5.8 | C4: 2.2 | D4: 1.8 | E4: 5.5 | F4: 7 | G4: 8 | H4: 9.8765532 | I4: 23000 | J4: 4 | K4: 120000 | L4: 101036.77 | M4: 2.5 | N4: 2.7 | O4: 10.5 | P4: 11.482942
A5: 44255 | B5: 5.9566089 | C5: 2.3852357 | D5: 2.0249695 | E5: 5.9147403 | F5: 7.2244145 | G5: 9.3906853 | H5: 10.865306 | I5: 23069.474 | J5: 4 | K5: 124976.88 | L5: 102556.69 | M5: 2.7322546 | N5: 2.9322546 | O5: 10.729617 | P5: 11.574094
A6: 44286 | B6: 6.1100271 | C6: 2.5685568 | D6: 2.2464405 | E6: 6.3179867 | F6: 7.4453271 | G6: 10.725928 | H6: 11.699961 | I6: 23137.799 | J6: 4 | K6: 129815.84 | L6: 103724.62 | M6: 2.9580726 | N6: 3.1580726 | O6: 10.956939 | P6: 11.650594
A7: 44316 | B7: 6.257129 | C7: 2.7480726 | D7: 2.4610011 | E7: 6.6985638 | F7: 7.6592906 | G7: 11.952497 | H7: 12.347244 | I7: 23203.856 | J7: 4 | K7: 134382.77 | L7: 104522.33 | M7: 3.1711958 | N7: 3.3711958 | O7: 11.179696 | P7: 11.711811
A8: 44347 | B8: 6.3949176 | C8: 2.9219389 | D8: 2.6654101 | E8: 7.0459245 | F8: 7.862966 | G8: 13.021493 | H8: 12.781349 | I8: 23266.592 | J8: 4 | K8: 138551.09 | L8: 104937.37 | M8: 3.3657177 | N8: 3.5657177 | O8: 11.395662 | P8: 11.757238
A9: 44377 | B9: 6.5205857 | C9: 3.0883815 | D9: 2.8566757 | E9: 7.3504421 | F9: 8.0531751 | G9: 13.890297 | H9: 12.98497 | I9: 23325.044 | J9: 4 | K9: 142205.31 | L9: 104963.28 | M9: 3.5362476 | N9: 3.7362476 | O9: 11.602679 | P9: 11.786501
A10: 44408 | B10: 6.6315729 | C10: 3.2457177 | D10: 3.0321255 | E10: 7.6036775 | F10: 8.2269498 | G10: 14.524274 | H10: 12.949989 | I10: 23378.368 | J10: 4 | K10: 145244.13 | L10: 104599.65 | M10: 3.6780594 | N10: 3.8780594 | O10: 11.798678 | P10: 11.799358
A11: 44439 | B11: 6.7256181 | C11: 3.392377 | D11: 3.189467 | E11: 7.7986124 | F11: 8.3815783 | G11: 14.898148 | H11: 12.677801 | I11: 23425.861 | J11: 4 | K11: 147583.35 | L11: 103852.14 | M11: 3.787223 | N11: 3.987223 | O11: 11.981701 | P11: 11.795702
A12: 44469 | B12: 6.8008052 | C12: 3.5269207 | D12: 3.3268354 | E12: 7.9298448 | F12: 8.5146478 | G12: 14.997015 | H12: 12.179256 | I12: 23466.984 | J12: 4 | K12: 149158.14 | L12: 102732.44 | M12: 3.8607131 | N12: 4.0607131 | O12: 12.149919 | P12: 11.775565
A13: 44500 | B13: 6.8556024 | C13: 3.6480594 | D13: 3.4428289 | E13: 7.9937375 | F13: 8.6240817 | G13: 14.816933 | H13: 11.474231 | I13: 23501.374 | J13: 4 | K13: 149924.85 | L13: 101257.99 | M13: 3.896493 | N13: 4.096493 | O13: 12.301652 | P13: 11.739112
A14: 44530 | B14: 6.8888934 | C14: 3.7546691 | D14: 3.5365286 | E14: 7.9885199 | F14: 8.7081723 | G14: 14.365082 | H14: 10.590833 | I14: 23528.852 | J14: 4 | K14: 149862.24 | L14: 99451.83 | M14: 3.8935711 | N14: 4.0935711 | O14: 12.435383 | P14: 11.686644
A15: 44561 | B15: 6.8999998 | C15: 3.845805 | D15: 3.6075043 | E15: 7.9143366 | F15: 8.7656075 | G15: 13.659475 | H15: 9.5642793 | I15: 23549.434 | J15: 4 | K15: 148972.04 | L15: 97342.126 | M15: 3.8520285 | N15: 4.0520285 | O15: 12.549777 | P15: 11.618595
... A67: 46142 | B67: 7.0533303 | C67: 5.0097812 | D67: 4.6165058 | E67: 3.3007606 | F67: 8.7996024 | G67: 8.2353613 | H67: 10.051969 | I67: 24544.076 | J67: 4.25 | K67: 93609.127 | L67: 93062.448 | M67: 2.2684259 | N67: 2.4684259 | O67: 10.538672 | P67: 10.659268

Sheet INPUT_INDUSTRY
A1: INPUT_INDUSTRY - Quarterly Peer Bank Metrics | B1: INPUT_INDUSTRY - Quarterly Peer Bank Metrics | C1: INPUT_INDUSTRY - Quarterly Peer Bank Metrics | D1: INPUT_INDUSTRY - Quarterly Peer Bank Metrics | E1: INPUT_INDUSTRY - Quarterly Peer Bank Metrics | F1: INPUT_INDUSTRY - Quarterly Peer Bank Metrics | G1: INPUT_INDUSTRY - Quarterly Peer Bank Metrics | H1: INPUT_INDUSTRY - Quarterly Peer Bank Metrics | I1: INPUT_INDUSTRY - Quarterly Peer Bank Metrics | J1: INPUT_INDUSTRY - Quarterly Peer Bank Metrics | K1: INPUT_INDUSTRY - Quarterly Peer Bank Metrics | L1: INPUT_INDUSTRY - Quarterly Peer Bank Metrics
A3: date | B3: bank | C3: loan_growth | D3: deposit_growth | E3: nim | F3: casa | G3: npl | H3: ldr | I3: car | J3: roa | K3: roe | L3: cir
A4: 44286 | B4: ABB | C4: 11 | D4: 10 | E4: 3 | F4: 16 | G4: 2 | H4: 78 | I4: 11 | J4: 1.2 | K4: 14 | L4: 38
A5: 44286 | B5: ACB | C5: 12.694808 | D5: 10.957605 | E5: 3.3543677 | F5: 21.781584 | G5: 2.2103677 | H5: 82.797128 | I5: 12.441471 | J5: 1.4462206 | K5: 16.454389 | L5: 39.084413
A6: 44286 | B6: MBB | C6: 13.558851 | D6: 11.500953 | E6: 3.4193244 | F6: 24.255109 | G6: 2.2273244 | H6: 85.407355 | I6: 12.709297 | J6: 1.4963946 | K6: 17.63674 | L6: 38.807892
A7: 44286 | B7: TCB | C7: 13.763278 | D7: 11.716356 | E7: 3.20328 | F7: 24.124413 | G7: 2.03528 | H7: 85.787475 | I7: 11.84112 | J7: 1.361168 | K7: 17.782942 | L7: 36.74336
A8: 44286 | B8: VPB | C8: 13.782942 | D8: 11.841241 | E8: 2.9427994 | F8: 23.315814 | G8: 2.7107994 | H8: 84.746487 | I8: 10.793198 | J8: 1.1964796 | K8: 17.593876 | L8: 34.409593
A9: 44286 | B9: HDB | C9: 13.897969 | D9: 12.014648 | E9: 2.8802689 | F9: 22.986224 | G9: 1.7602689 | H9: 82.992361 | I9: 10.541076 | J9: 1.1561614 | K9: 17.490816 | L9: 33.923227
A10: 44286 | B10: VIB | C10: 13.89499 | D10: 12.12767 | E10: 3.0381461 | F10: 22.327892 | G10: 1.9301461 | H10: 80.5056 | I10: 11.170585 | J10: 1.2480877 | K10: 17.168595 | L10: 36.081754
A11: 44286 | B11: OCB | C11: 13.367972 | D11: 11.97381 | E11: 3.2122466 | F11: 19.769258 | G11: 3.0642466 | H11: 77.046084 | I11: 11.856987 | J11: 1.338548 | K11: 16.046172 | L11: 39.49096
A12: 44377 | B12: ABB | C12: 11.654389 | D12: 10.445327 | E12: 3.061851 | F12: 16.596008 | G12: 2.0817987 | H12: 79.23702 | I12: 11.165896 | J12: 1.2298004 | K12: 14.397339 | L12: 38.596008
A13: 44377 | B13: ACB | C13: 13.301618 | D13: 11.382938 | E13: 3.3812462 | F13: 22.32522 | G13: 2.2429845 | H13: 83.808194 | I13: 12.519445 | J13: 1.4598059 | K13: 16.816813 | L13: 39.356117
A14: 44377 | B14: MBB | C14: 14.080354 | D14: 11.889336 | E14: 3.3865183 | F14: 24.686526 | G14: 2.1807715 | H14: 85.944923 | I14: 12.62766 | J14: 1.4812745 | K14: 17.924351 | L14: 38.505489
A15: 44377 | B15: TCB | C15: 14.167048 | D15: 12.052305 | E15: 3.1409512 | F15: 24.396117 | G15: 1.952358 | H15: 85.71993 | I15: 11.674929 | J15: 1.3312439 | K15: 17.964078 | L15: 36.144878
... A171: 46112 | B171: OCB | C171: 13.091652 | D171: 10.409789 | E171: 2.9138568 | F171: 17.750381 | G171: 3.1228354 | H171: 82.792436 | I171: 10.411384 | J171: 1.0900015 | K171: 14.700254 | L171: 34.520029

Sheet INPUT_ABBANK
A1: INPUT_ABBANK - Monthly Business Performance | B1: INPUT_ABBANK - Monthly Business Performance | C1: INPUT_ABBANK - Monthly Business Performance | D1: INPUT_ABBANK - Monthly Business Performance | E1: INPUT_ABBANK - Monthly Business Performance | F1: INPUT_ABBANK - Monthly Business Performance | G1: INPUT_ABBANK - Monthly Business Performance | H1: INPUT_ABBANK - Monthly Business Performance | I1: INPUT_ABBANK - Monthly Business Performance | J1: INPUT_ABBANK - Monthly Business Performance | K1: INPUT_ABBANK - Monthly Business Performance | L1: INPUT_ABBANK - Monthly Business Performance | M1: INPUT_ABBANK - Monthly Business Performance | N1: INPUT_ABBANK - Monthly Business Performance | O1: INPUT_ABBANK - Monthly Business Performance
A3: date | B3: loan | C3: loan_growth | D3: deposit | E3: deposit_growth | F3: casa | G3: nim | H3: asset_yield | I3: cost_of_funds | J3: ldr | K3: npl | L3: provision_coverage | M3: cir | N3: pbt | O3: roa | P3: roe
A4: 44227 | B4: 86000 | C4: 9 | D4: 98000 | E4: 10.482942 | F4: 14 | G4: 3.05 | H4: 7.8 | I4: 4.9103677 | J4: 87.755102 | K4: 2 | L4: 81.731768 | M4: 42 | N4: 120 | O4: 0.8 | P4: 10.5
A5: 44255 | B5: 87148.004 | C5: 9.2439418 | D5: 98979.075 | E5: 10.604535 | F5: 14.199667 | G5: 3.0855929 | H5: 7.8311687 | I5: 4.9298612 | J5: 88.046896 | K5: 2.0436362 | L5: 82.129659 | M5: 42.374024 | N5: 126.31792 | O5: 0.81423717 | P5: 10.713558
A6: 44286 | B6: 88284.128 | C6: 9.484875 | D6: 99952.634 | E6: 10.697969 | F6: 14.397339 | G6: 3.1204607 | H6: 7.861851 | I6: 4.9429845 | J6: 88.325964 | K6: 2.0865914 | L6: 82.456313 | M6: 42.742212 | N6: 132.54389 | O6: 0.82818429 | P6: 10.922764
A7: 44316 | B7: 89396.964 | C7: 9.7198283 | D7: 100915.31 | E7: 10.761786 | F7: 14.59104 | G7: 3.153893 | H7: 7.8915681 | I7: 4.9493737 | J7: 88.586125 | K7: 2.1281954 | L7: 82.708465 | M7: 43.098818 | N7: 138.58851 | O7: 0.84155719 | P7: 11.123358
A8: 44347 | B8: 90476.034 | C8: 9.945904 | D8: 101862.04 | E8: 10.79499 | F8: 14.778837 | G8: 3.1852086 | H8: 7.9198564 | I8: 4.948852 | J8: 88.822127 | K8: 2.1677989 | L8: 82.883598 | M8: 43.438277 | N8: 144.3674 | O8: 0.85408342 | P8: 11.311251
A9: 44377 | B9: 91512.206 | C9: 10.160314 | D9: 102788.21 | E9: 10.797063 | F9: 14.958851 | G9: 3.2137695 | H9: 7.9462743 | I9: 4.9414337 | J9: 89.029865 | K9: 2.204784 | L9: 82.97996 | M9: 43.755292 | N9: 149.80354 | O9: 0.86550779 | P9: 11.482617
A10: 44408 | B10: 92498.059 | C10: 10.360414 | D10: 103689.77 | E10: 10.767972 | F10: 15.129285 | G10: 3.2389938 | H10: 7.9704097 | I10: 4.9273244 | J10: 89.206547 | K10: 2.2385736 | L10: 82.996589 | M10: 44.044916 | N10: 154.82942 | O10: 0.87559754 | P10: 11.633963
A11: 44439 | B11: 93428.175 | C11: 10.543735 | D11: 104563.33 | E11: 10.708172 | F11: 15.288435 | G11: 3.2603677 | H11: 7.9918859 | I11: 4.9069151 | J11: 89.350799 | K11: 2.2686402 | L11: 82.933318 | M11: 44.302631 | N11: 159.3889 | O11: 0.8841471 | P11: 11.762206
A12: 44469 | B12: 94299.36 | C12: 10.708018 | D12: 105406.33 | E12: 10.618595 | F12: 15.434712 | G12: 3.2774557 | H12: 8.0103677 | I12: 4.8807715 | J12: 89.462715 | K12: 2.2945148 | L12: 82.790781 | M12: 44.524413 | N12: 163.43876 | O12: 0.89098229 | P12: 11.864734
A13: 44500 | B13: 95110.771 | C13: 10.851236 | D13: 106216.99 | E13: 10.50064 | F13: 15.566654 | G13: 3.2899096 | H13: 8.0255669 | I13: 4.849618 | J13: 89.543837 | K13: 2.3157937 | L13: 82.570401 | M13: 44.706803 | N13: 166.9499 | O13: 0.89596386 | P13: 11.939458
A14: 44530 | B14: 95863.946 | C14: 10.971623 | D14: 106994.49 | E14: 10.356146 | F14: 15.682942 | G14: 3.2974758 | H14: 8.0372462 | I14: 4.8143182 | J14: 89.597087 | K14: 2.3321446 | L14: 82.274379 | M14: 44.846954 | N14: 169.90816 | O14: 0.89899031 | P14: 11.984855
A15: 44561 | B15: 96562.745 | C15: 11.067694 | D15: 107738.88 | E15: 10.18737 | F15: 15.782415 | G15: 3.3 | H15: 8.0452233 | I15: 4.7758501 | J15: 89.626645 | K15: 2.3433126 | L15: 81.905675 | M15: 44.942679 | N15: 172.31469 | O15: 0.89999998 | P15: 12
... A67: 46142 | B67: 139600.43 | C67: 10.445371 | D67: 146084.37 | E67: 9.8449958 | F67: 14.033628 | G67: 3.1530296 | H67: 8.0499448 | I67: 4.481137 | J67: 95.561516 | K67: 2.3499227 | L67: 81.803493 | M67: 44.999337 | N67: 291.40608 | O67: 0.84121185 | P67: 11.118178

Sheet INPUT_TREASURY
A1: INPUT_TREASURY - Daily/Monthly Treasury Portfolio | B1: INPUT_TREASURY - Daily/Monthly Treasury Portfolio | C1: INPUT_TREASURY - Daily/Monthly Treasury Portfolio | D1: INPUT_TREASURY - Daily/Monthly Treasury Portfolio | E1: INPUT_TREASURY - Daily/Monthly Treasury Portfolio | F1: INPUT_TREASURY - Daily/Monthly Treasury Portfolio | G1: INPUT_TREASURY - Daily/Monthly Treasury Portfolio | H1: INPUT_TREASURY - Daily/Monthly Treasury Portfolio | I1: INPUT_TREASURY - Daily/Monthly Treasury Portfolio | J1: INPUT_TREASURY - Daily/Monthly Treasury Portfolio
A3: date | B3: portfolio_size | C3: duration | D3: dv01 | E3: mtm_pnl | F3: fx_position | G3: usd_assets | H3: usd_liabilities | I3: liquidity_gap_7d | J3: liquidity_gap_30d
A4: 44227 | B4: 50000 | C4: 2.1 | D4: 4.7 | E4: 0 | F4: 0 | G4: 2500 | H4: 2400 | I4: -1500 | J4: 3000
A5: 44255 | B5: 50000 | C5: 2.1436362 | D5: 4.7798667 | E5: 13.271691 | F5: 2.2176526 | G5: 2524.9349 | H5: 2425.6269 | I5: -1400.6653 | J5: 3085.423
A6: 44286 | B6: 50000 | C6: 2.1865914 | D6: 4.8589355 | E6: 26.175576 | F6: 4.4079549 | G6: 2549.4808 | H6: 2450.7317 | I6: -1305.2908 | J6: 3169.1057
A7: 44316 | B7: 50000 | C7: 2.2281954 | D7: 4.9364162 | E7: 38.354043 | F7: 6.5438939 | G7: 2573.2545 | H7: 2474.8029 | I7: -1217.6788 | J7: 3249.3431
A8: 44347 | B8: 50000 | C8: 2.2677989 | D8: 5.0115347 | E8: 49.469584 | F8: 8.5991273 | G8: 2595.8851 | H8: 2497.3502 | I8: -1141.322 | J8: 3324.5005
A9: 44377 | B9: 50000 | C9: 2.304784 | D9: 5.0835404 | E9: 59.214148 | F9: 10.548308 | G9: 2617.0195 | H9: 2517.914 | I9: -1079.2645 | J9: 3393.0467
A10: 44408 | B10: 50000 | C10: 2.3385736 | D10: 5.151714 | E10: 67.317679 | F10: 12.367396 | G10: 2636.3278 | H10: 2536.0756 | I10: -1033.9805 | J10: 3453.5852
A11: 44439 | B11: 50000 | C11: 2.3686402 | D11: 5.2153741 | E11: 73.555598 | F11: 14.033958 | G11: 2653.5087 | H11: 2551.4648 | I11: -1007.2751 | J11: 3504.8826
A12: 44469 | B12: 50000 | C12: 2.3945148 | D12: 5.2738849 | E12: 77.755032 | F12: 15.527438 | G12: 2668.2942 | H12: 2563.7681 | I12: -1000.2132 | J12: 3545.8937
A13: 44500 | B13: 50000 | C13: 2.4157937 | D13: 5.3266615 | E13: 79.799599 | F13: 16.82942 | G13: 2680.4535 | H13: 2572.7349 | I13: -1013.0762 | J13: 3575.7831
A14: 44530 | B14: 50000 | C14: 2.4321446 | D14: 5.3731768 | E14: 79.632637 | F14: 17.923844 | G14: 2689.7969 | H14: 2578.1826 | I14: -1045.3513 | J14: 3593.9418
A15: 44561 | B15: 50000 | C15: 2.4433126 | D15: 5.4129659 | E15: 77.258772 | F15: 18.797214 | G15: 2696.1786 | H15: 2580 | I15: -1095.7518 | J15: 3599.9999
... A67: 46142 | B67: 50000 | C67: 2.4499227 | D67: 4.7134511 | E67: -70.375661 | F67: 13.139732 | G67: 2699.9558 | H67: 2474.1813 | I67: -1483.1885 | J67: 3247.2711

Sheet INPUT_SCENARIO
A1: INPUT_SCENARIO - Stress Assumptions | B1: INPUT_SCENARIO - Stress Assumptions | C1: INPUT_SCENARIO - Stress Assumptions | D1: INPUT_SCENARIO - Stress Assumptions | E1: INPUT_SCENARIO - Stress Assumptions
A3: scenario | B3: shock_rate_bps | C3: shock_fx_pct | D3: shock_npl_pct | E3: description
A4: base | B4: 0 | C4: 0 | D4: 0 | E4: Không có cú sốc; dùng làm baseline
A5: stress | B5: 100 | C5: 2 | D5: 1 | E5: Thanh khoản thắt chặt, tỷ giá chịu áp lực vừa
A6: crisis | B6: 200 | C6: 5 | D6: 2 | E6: Cú sốc lãi suất/tỷ giá mạnh, NPL tăng rõ

Sheet PROC_MACRO
A1: PROC_MACRO - Macro Signals & Score | B1: PROC_MACRO - Macro Signals & Score | C1: PROC_MACRO - Macro Signals & Score | D1: PROC_MACRO - Macro Signals & Score | E1: PROC_MACRO - Macro Signals & Score | F1: PROC_MACRO - Macro Signals & Score | G1: PROC_MACRO - Macro Signals & Score | H1: PROC_MACRO - Macro Signals & Score | I1: PROC_MACRO - Macro Signals & Score | J1: PROC_MACRO - Macro Signals & Score | K1: PROC_MACRO - Macro Signals & Score
A3: date | B3: cpi | C3: usd_vnd | D3: vnibor_on | E3: credit_growth | F3: deposit_growth | G3: fx_mom_pct | H3: credit_deposit_gap | I3: liquidity_pressure | J3: inflation_pressure | K3: macro_score
A4: =INPUT_MACRO!A4 -> 44227 | B4: =INPUT_MACRO!C4 -> 2.2 | C4: =INPUT_MACRO!I4 -> 23000 | D4: =INPUT_MACRO!M4 -> 2.5 | E4: =INPUT_MACRO!O4 -> 10.5 | F4: =INPUT_MACRO!P4 -> 11.482942 | G4: =0 -> 0 | H4: =E4-F4 -> -0.98294197 | I4: =IF(D4>=CONFIG!B7,100,IF(D4>=CONFIG!B6,65,30)) -> 30 | J4: =IF(B4>=4.5,100,IF(B4>=3.5,65,30)) -> 30 | K4: =MAX(0,100-0.35*I4-0.35*J4-0.3*ABS(G4)*15) -> 79
A5: =INPUT_MACRO!A5 -> 44255 | B5: =INPUT_MACRO!C5 -> 2.3852357 | C5: =INPUT_MACRO!I5 -> 23069.474 | D5: =INPUT_MACRO!M5 -> 2.7322546 | E5: =INPUT_MACRO!O5 -> 10.729617 | F5: =INPUT_MACRO!P5 -> 11.574094 | G5: =IFERROR((C5/C4-1)*100,0) -> 0.30206101 | H5: =E5-F5 -> -0.84447712 | I5: =IF(D5>=CONFIG!B7,100,IF(D5>=CONFIG!B6,65,30)) -> 30 | J5: =IF(B5>=4.5,100,IF(B5>=3.5,65,30)) -> 30 | K5: =MAX(0,100-0.35*I5-0.35*J5-0.3*ABS(G5)*15) -> 77.640725
A6: =INPUT_MACRO!A6 -> 44286 | B6: =INPUT_MACRO!C6 -> 2.5685568 | C6: =INPUT_MACRO!I6 -> 23137.799 | D6: =INPUT_MACRO!M6 -> 2.9580726 | E6: =INPUT_MACRO!O6 -> 10.956939 | F6: =INPUT_MACRO!P6 -> 11.650594 | G6: =IFERROR((C6/C5-1)*100,0) -> 0.29616905 | H6: =E6-F6 -> -0.69365469 | I6: =IF(D6>=CONFIG!B7,100,IF(D6>=CONFIG!B6,65,30)) -> 30 | J6: =IF(B6>=4.5,100,IF(B6>=3.5,65,30)) -> 30 | K6: =MAX(0,100-0.35*I6-0.35*J6-0.3*ABS(G6)*15) -> 77.667239
A7: =INPUT_MACRO!A7 -> 44316 | B7: =INPUT_MACRO!C7 -> 2.7480726 | C7: =INPUT_MACRO!I7 -> 23203.856 | D7: =INPUT_MACRO!M7 -> 3.1711958 | E7: =INPUT_MACRO!O7 -> 11.179696 | F7: =INPUT_MACRO!P7 -> 11.711811 | G7: =IFERROR((C7/C6-1)*100,0) -> 0.28549695 | H7: =E7-F7 -> -0.53211421 | I7: =IF(D7>=CONFIG!B7,100,IF(D7>=CONFIG!B6,65,30)) -> 30 | J7: =IF(B7>=4.5,100,IF(B7>=3.5,65,30)) -> 30 | K7: =MAX(0,100-0.35*I7-0.35*J7-0.3*ABS(G7)*15) -> 77.715264
A8: =INPUT_MACRO!A8 -> 44347 | B8: =INPUT_MACRO!C8 -> 2.9219389 | C8: =INPUT_MACRO!I8 -> 23266.592 | D8: =INPUT_MACRO!M8 -> 3.3657177 | E8: =INPUT_MACRO!O8 -> 11.395662 | F8: =INPUT_MACRO!P8 -> 11.757238 | G8: =IFERROR((C8/C7-1)*100,0) -> 0.27036914 | H8: =E8-F8 -> -0.36157582 | I8: =IF(D8>=CONFIG!B7,100,IF(D8>=CONFIG!B6,65,30)) -> 30 | J8: =IF(B8>=4.5,100,IF(B8>=3.5,65,30)) -> 30 | K8: =MAX(0,100-0.35*I8-0.35*J8-0.3*ABS(G8)*15) -> 77.783339
A9: =INPUT_MACRO!A9 -> 44377 | B9: =INPUT_MACRO!C9 -> 3.0883815 | C9: =INPUT_MACRO!I9 -> 23325.044 | D9: =INPUT_MACRO!M9 -> 3.5362476 | E9: =INPUT_MACRO!O9 -> 11.602679 | F9: =INPUT_MACRO!P9 -> 11.786501 | G9: =IFERROR((C9/C8-1)*100,0) -> 0.25122614 | H9: =E9-F9 -> -0.18382221 | I9: =IF(D9>=CONFIG!B7,100,IF(D9>=CONFIG!B6,65,30)) -> 30 | J9: =IF(B9>=4.5,100,IF(B9>=3.5,65,30)) -> 30 | K9: =MAX(0,100-0.35*I9-0.35*J9-0.3*ABS(G9)*15) -> 77.869482
A10: =INPUT_MACRO!A10 -> 44408 | B10: =INPUT_MACRO!C10 -> 3.2457177 | C10: =INPUT_MACRO!I10 -> 23378.368 | D10: =INPUT_MACRO!M10 -> 3.6780594 | E10: =INPUT_MACRO!O10 -> 11.798678 | F10: =INPUT_MACRO!P10 -> 11.799358 | G10: =IFERROR((C10/C9-1)*100,0) -> 0.22861064 | H10: =E10-F10 -> -0.00068013968 | I10: =IF(D10>=CONFIG!B7,100,IF(D10>=CONFIG!B6,65,30)) -> 30 | J10: =IF(B10>=4.5,100,IF(B10>=3.5,65,30)) -> 30 | K10: =MAX(0,100-0.35*I10-0.35*J10-0.3*ABS(G10)*15) -> 77.971252
A11: =INPUT_MACRO!A11 -> 44439 | B11: =INPUT_MACRO!C11 -> 3.392377 | C11: =INPUT_MACRO!I11 -> 23425.861 | D11: =INPUT_MACRO!M11 -> 3.787223 | E11: =INPUT_MACRO!O11 -> 11.981701 | F11: =INPUT_MACRO!P11 -> 11.795702 | G11: =IFERROR((C11/C10-1)*100,0) -> 0.20315147 | H11: =E11-F11 -> 0.18599821 | I11: =IF(D11>=CONFIG!B7,100,IF(D11>=CONFIG!B6,65,30)) -> 30 | J11: =IF(B11>=4.5,100,IF(B11>=3.5,65,30)) -> 30 | K11: =MAX(0,100-0.35*I11-0.35*J11-0.3*ABS(G11)*15) -> 78.085818
A12: =INPUT_MACRO!A12 -> 44469 | B12: =INPUT_MACRO!C12 -> 3.5269207 | C12: =INPUT_MACRO!I12 -> 23466.984 | D12: =INPUT_MACRO!M12 -> 3.8607131 | E12: =INPUT_MACRO!O12 -> 12.149919 | F12: =INPUT_MACRO!P12 -> 11.775565 | G12: =IFERROR((C12/C11-1)*100,0) -> 0.17554629 | H12: =E12-F12 -> 0.37435395 | I12: =IF(D12>=CONFIG!B7,100,IF(D12>=CONFIG!B6,65,30)) -> 30 | J12: =IF(B12>=4.5,100,IF(B12>=3.5,65,30)) -> 65 | K12: =MAX(0,100-0.35*I12-0.35*J12-0.3*ABS(G12)*15) -> 65.960042
A13: =INPUT_MACRO!A13 -> 44500 | B13: =INPUT_MACRO!C13 -> 3.6480594 | C13: =INPUT_MACRO!I13 -> 23501.374 | D13: =INPUT_MACRO!M13 -> 3.896493 | E13: =INPUT_MACRO!O13 -> 12.301652 | F13: =INPUT_MACRO!P13 -> 11.739112 | G13: =IFERROR((C13/C12-1)*100,0) -> 0.14654321 | H13: =E13-F13 -> 0.56253999 | I13: =IF(D13>=CONFIG!B7,100,IF(D13>=CONFIG!B6,65,30)) -> 30 | J13: =IF(B13>=4.5,100,IF(B13>=3.5,65,30)) -> 65 | K13: =MAX(0,100-0.35*I13-0.35*J13-0.3*ABS(G13)*15) -> 66.090556
A14: =INPUT_MACRO!A14 -> 44530 | B14: =INPUT_MACRO!C14 -> 3.7546691 | C14: =INPUT_MACRO!I14 -> 23528.852 | D14: =INPUT_MACRO!M14 -> 3.8935711 | E14: =INPUT_MACRO!O14 -> 12.435383 | F14: =INPUT_MACRO!P14 -> 11.686644 | G14: =IFERROR((C14/C13-1)*100,0) -> 0.11692186 | H14: =E14-F14 -> 0.74873921 | I14: =IF(D14>=CONFIG!B7,100,IF(D14>=CONFIG!B6,65,30)) -> 30 | J14: =IF(B14>=4.5,100,IF(B14>=3.5,65,30)) -> 65 | K14: =MAX(0,100-0.35*I14-0.35*J14-0.3*ABS(G14)*15) -> 66.223852
A15: =INPUT_MACRO!A15 -> 44561 | B15: =INPUT_MACRO!C15 -> 3.845805 | C15: =INPUT_MACRO!I15 -> 23549.434 | D15: =INPUT_MACRO!M15 -> 3.8520285 | E15: =INPUT_MACRO!O15 -> 12.549777 | F15: =INPUT_MACRO!P15 -> 11.618595 | G15: =IFERROR((C15/C14-1)*100,0) -> 0.087474196 | H15: =E15-F15 -> 0.93118207 | I15: =IF(D15>=CONFIG!B7,100,IF(D15>=CONFIG!B6,65,30)) -> 30 | J15: =IF(B15>=4.5,100,IF(B15>=3.5,65,30)) -> 65 | K15: =MAX(0,100-0.35*I15-0.35*J15-0.3*ABS(G15)*15) -> 66.356366
A16: =INPUT_MACRO!A16 -> 44592 | B16: =INPUT_MACRO!C16 -> 3.9207131 | C16: =INPUT_MACRO!I16 -> 23563.324 | D16: =INPUT_MACRO!M16 -> 3.7730164 | E16: =INPUT_MACRO!O16 -> 12.64369 | F16: =INPUT_MACRO!P16 -> 11.535526 | G16: =IFERROR((C16/C15-1)*100,0) -> 0.058985254 | H16: =E16-F16 -> 1.1081636 | I16: =IF(D16>=CONFIG!B7,100,IF(D16>=CONFIG!B6,65,30)) -> 30 | J16: =IF(B16>=4.5,100,IF(B16>=3.5,65,30)) -> 65 | K16: =MAX(0,100-0.35*I16-0.35*J16-0.3*ABS(G16)*15) -> 66.484566
A17: =INPUT_MACRO!A17 -> 44620 | B17: =INPUT_MACRO!C17 -> 3.9788395 | C17: =INPUT_MACRO!I17 -> 23570.915 | D17: =INPUT_MACRO!M17 -> 3.6587245 | E17: =INPUT_MACRO!O17 -> 12.716184 | F17: =INPUT_MACRO!P17 -> 11.438124 | G17: =IFERROR((C17/C16-1)*100,0) -> 0.032214178 | H17: =E17-F17 -> 1.2780594 | I17: =IF(D17>=CONFIG!B7,100,IF(D17>=CONFIG!B6,65,30)) -> 30 | J17: =IF(B17>=4.5,100,IF(B17>=3.5,65,30)) -> 65 | K17: =MAX(0,100-0.35*I17-0.35*J17-0.3*ABS(G17)*15) -> 66.605036
A18: =INPUT_MACRO!A18 -> 44651 | B18: =INPUT_MACRO!C18 -> 4.0198374 | C18: =INPUT_MACRO!I18 -> 23572.771 | D18: =INPUT_MACRO!M18 -> 3.5123202 | E18: =INPUT_MACRO!O18 -> 12.766534 | F18: =INPUT_MACRO!P18 -> 11.327194 | G18: =IFERROR((C18/C17-1)*100,0) -> 0.0078757333 | H18: =E18-F18 -> 1.4393408 | I18: =IF(D18>=CONFIG!B7,100,IF(D18>=CONFIG!B6,65,30)) -> 30 | J18: =IF(B18>=4.5,100,IF(B18>=3.5,65,30)) -> 65 | K18: =MAX(0,100-0.35*I18-0.35*J18-0.3*ABS(G18)*15) -> 66.714559
A19: =INPUT_MACRO!A19 -> 44681 | B19: =INPUT_MACRO!C19 -> 4.0435711 | C19: =INPUT_MACRO!I19 -> 23569.618 | D19: =INPUT_MACRO!M19 -> 3.337861 | E19: =INPUT_MACRO!O19 -> 12.794238 | F19: =INPUT_MACRO!P19 -> 11.20365 | G19: =IFERROR((C19/C18-1)*100,0) -> -0.013377444 | H19: =E19-F19 -> 1.5905884 | I19: =IF(D19>=CONFIG!B7,100,IF(D19>=CONFIG!B6,65,30)) -> 30 | J19: =IF(B19>=4.5,100,IF(B19>=3.5,65,30)) -> 65 | K19: =MAX(0,100-0.35*I19-0.35*J19-0.3*ABS(G19)*15) -> 66.689801
A20: =INPUT_MACRO!A20 -> 44712 | B20: =INPUT_MACRO!C20 -> 4.050118 | C20: =INPUT_MACRO!I20 -> 23562.318 | D20: =INPUT_MACRO!M20 -> 3.1401817 | E20: =INPUT_MACRO!O20 -> 12.799019 | F20: =INPUT_MACRO!P20 -> 11.068514 | G20: =IFERROR((C20/C19-1)*100,0) -> -0.030971564 | H20: =E20-F20 -> 1.7305051 | I20: =IF(D20>=CONFIG!B7,100,IF(D20>=CONFIG!B6,65,30)) -> 30 | J20: =IF(B20>=4.5,100,IF(B20>=3.5,65,30)) -> 65 | K20: =MAX(0,100-0.35*I20-0.35*J20-0.3*ABS(G20)*15) -> 66.610628
A21: =INPUT_MACRO!A21 -> 44742 | B21: =INPUT_MACRO!C21 -> 4.0397672 | C21: =INPUT_MACRO!I21 -> 23551.85 | D21: =INPUT_MACRO!M21 -> 2.9247607 | E21: =INPUT_MACRO!O21 -> 12.780829 | F21: =INPUT_MACRO!P21 -> 10.922902 | G21: =IFERROR((C21/C20-1)*100,0) -> -0.044427037 | H21: =E21-F21 -> 1.8579272 | I21: =IF(D21>=CONFIG!B7,100,IF(D21>=CONFIG!B6,65,30)) -> 30 | J21: =IF(B21>=4.5,100,IF(B21>=3.5,65,30)) -> 65 | K21: =MAX(0,100-0.35*I21-0.35*J21-0.3*ABS(G21)*15) -> 66.550078
A22: =INPUT_MACRO!A22 -> 44773 | B22: =INPUT_MACRO!C22 -> 4.0130164 | C22: =INPUT_MACRO!I22 -> 23539.28 | D22: =INPUT_MACRO!M22 -> 2.697568 | E22: =INPUT_MACRO!O22 -> 12.73985 | F22: =INPUT_MACRO!P22 -> 10.768016 | G22: =IFERROR((C22/C21-1)*100,0) -> -0.053372091 | H22: =E22-F22 -> 1.9718338 | I22: =IF(D22>=CONFIG!B7,100,IF(D22>=CONFIG!B6,65,30)) -> 30 | J22: =IF(B22>=4.5,100,IF(B22>=3.5,65,30)) -> 65 | K22: =MAX(0,100-0.35*I22-0.35*J22-0.3*ABS(G22)*15) -> 66.509826
A23: =INPUT_MACRO!A23 -> 44804 | B23: =INPUT_MACRO!C23 -> 3.9705655 | C23: =INPUT_MACRO!I23 -> 23525.732 | D23: =INPUT_MACRO!M23 -> 2.4649001 | E23: =INPUT_MACRO!O23 -> 12.67649 | F23: =INPUT_MACRO!P23 -> 10.605135 | G23: =IFERROR((C23/C22-1)*100,0) -> -0.057554218 | H23: =E23-F23 -> 2.0713552 | I23: =IF(D23>=CONFIG!B7,100,IF(D23>=CONFIG!B6,65,30)) -> 30 | J23: =IF(B23>=4.5,100,IF(B23>=3.5,65,30)) -> 65 | K23: =MAX(0,100-0.35*I23-0.35*J23-0.3*ABS(G23)*15) -> 66.491006
A24: =INPUT_MACRO!A24 -> 44834 | B24: =INPUT_MACRO!C24 -> 3.9133081 | C24: =INPUT_MACRO!I24 -> 23512.358 | D24: =INPUT_MACRO!M24 -> 2.2332049 | E24: =INPUT_MACRO!O24 -> 12.591384 | F24: =INPUT_MACRO!P24 -> 10.435605 | G24: =IFERROR((C24/C23-1)*100,0) -> -0.056849003 | H24: =E24-F24 -> 2.1557793 | I24: =IF(D24>=CONFIG!B7,100,IF(D24>=CONFIG!B6,65,30)) -> 30 | J24: =IF(B24>=4.5,100,IF(B24>=3.5,65,30)) -> 65 | K24: =MAX(0,100-0.35*I24-0.35*J24-0.3*ABS(G24)*15) -> 66.494179
A25: =INPUT_MACRO!A25 -> 44865 | B25: =INPUT_MACRO!C25 -> 3.8423202 | C25: =INPUT_MACRO!I25 -> 23500.304 | D25: =INPUT_MACRO!M25 -> 2.0089035 | E25: =INPUT_MACRO!O25 -> 12.485382 | F25: =INPUT_MACRO!P25 -> 10.260825 | G25: =IFERROR((C25/C24-1)*100,0) -> -0.051265876 | H25: =E25-F25 -> 2.2245562 | I25: =IF(D25>=CONFIG!B7,100,IF(D25>=CONFIG!B6,65,30)) -> 30 | J25: =IF(B25>=4.5,100,IF(B25>=3.5,65,30)) -> 65 | K25: =MAX(0,100-0.35*I25-0.35*J25-0.3*ABS(G25)*15) -> 66.519304
A26: =INPUT_MACRO!A26 -> 44895 | B26: =INPUT_MACRO!C26 -> 3.7588475 | C26: =INPUT_MACRO!I26 -> 23490.681 | D26: =INPUT_MACRO!M26 -> 1.7982121 | E26: =INPUT_MACRO!O26 -> 12.359542 | F26: =INPUT_MACRO!P26 -> 10.08224 | G26: =IFERROR((C26/C25-1)*100,0) -> -0.040950343 | H26: =E26-F26 -> 2.2773017 | I26: =IF(D26>=CONFIG!B7,100,IF(D26>=CONFIG!B6,65,30)) -> 30 | J26: =IF(B26>=4.5,100,IF(B26>=3.5,65,30)) -> 65 | K26: =MAX(0,100-0.35*I26-0.35*J26-0.3*ABS(G26)*15) -> 66.565723
A27: =INPUT_MACRO!A27 -> 44926 | B27: =INPUT_MACRO!C27 -> 3.6642892 | C27: =INPUT_MACRO!I27 -> 23484.53 | D27: =INPUT_MACRO!M27 -> 1.6069698 | E27: =INPUT_MACRO!O27 -> 12.215122 | F27: =INPUT_MACRO!P27 -> 9.9013237 | G27: =IFERROR((C27/C26-1)*100,0) -> -0.026182363 | H27: =E27-F27 -> 2.3137983 | I27: =IF(D27>=CONFIG!B7,100,IF(D27>=CONFIG!B6,65,30)) -> 30 | J27: =IF(B27>=4.5,100,IF(B27>=3.5,65,30)) -> 65 | K27: =MAX(0,100-0.35*I27-0.35*J27-0.3*ABS(G27)*15) -> 66.632179
A28: =INPUT_MACRO!A28 -> 44957 | B28: =INPUT_MACRO!C28 -> 3.5601817 | C28: =INPUT_MACRO!I28 -> 23482.799 | D28: =INPUT_MACRO!M28 -> 1.4404765 | E28: =INPUT_MACRO!O28 -> 12.053565 | F28: =INPUT_MACRO!P28 -> 9.7195706 | G28: =IFERROR((C28/C27-1)*100,0) -> -0.0073705815 | H28: =E28-F28 -> 2.3339947 | I28: =IF(D28>=CONFIG!B7,100,IF(D28>=CONFIG!B6,65,30)) -> 30 | J28: =IF(B28>=4.5,100,IF(B28>=3.5,65,30)) -> 65 | K28: =MAX(0,100-0.35*I28-0.35*J28-0.3*ABS(G28)*15) -> 66.716832
A29: =INPUT_MACRO!A29 -> 44985 | B29: =INPUT_MACRO!C29 -> 3.4481788 | C29: =INPUT_MACRO!I29 -> 23486.312 | D29: =INPUT_MACRO!M29 -> 1.3033463 | E29: =INPUT_MACRO!O29 -> 11.876486 | F29: =INPUT_MACRO!P29 -> 9.5384818 | G29: =IFERROR((C29/C28-1)*100,0) -> 0.014957638 | H29: =E29-F29 -> 2.3380041 | I29: =IF(D29>=CONFIG!B7,100,IF(D29>=CONFIG!B6,65,30)) -> 30 | J29: =IF(B29>=4.5,100,IF(B29>=3.5,65,30)) -> 30 | K29: =MAX(0,100-0.35*I29-0.35*J29-0.3*ABS(G29)*15) -> 78.932691
A30: =INPUT_MACRO!A30 -> 45016 | B30: =INPUT_MACRO!C30 -> 3.3300319 | C30: =INPUT_MACRO!I30 -> 23495.746 | D30: =INPUT_MACRO!M30 -> 1.1993797 | E30: =INPUT_MACRO!O30 -> 11.685653 | F30: =INPUT_MACRO!P30 -> 9.3595528 | G30: =IFERROR((C30/C29-1)*100,0) -> 0.040170319 | H30: =E30-F30 -> 2.3261004 | I30: =IF(D30>=CONFIG!B7,100,IF(D30>=CONFIG!B6,65,30)) -> 30 | J30: =IF(B30>=4.5,100,IF(B30>=3.5,65,30)) -> 30 | K30: =MAX(0,100-0.35*I30-0.35*J30-0.3*ABS(G30)*15) -> 78.819234
A31: =INPUT_MACRO!A31 -> 45046 | B31: =INPUT_MACRO!C31 -> 3.207568 | C31: =INPUT_MACRO!I31 -> 23511.617 | D31: =INPUT_MACRO!M31 -> 1.1314578 | E31: =INPUT_MACRO!O31 -> 11.482974 | F31: =INPUT_MACRO!P31 -> 9.1842613 | G31: =IFERROR((C31/C30-1)*100,0) -> 0.067548805 | H31: =E31-F31 -> 2.2987124 | I31: =IF(D31>=CONFIG!B7,100,IF(D31>=CONFIG!B6,65,30)) -> 30 | J31: =IF(B31>=4.5,100,IF(B31>=3.5,65,30)) -> 30 | K31: =MAX(0,100-0.35*I31-0.35*J31-0.3*ABS(G31)*15) -> 78.69603
A32: =INPUT_MACRO!A32 -> 45077 | B32: =INPUT_MACRO!C32 -> 3.0826676 | C32: =INPUT_MACRO!I32 -> 23534.261 | D32: =INPUT_MACRO!M32 -> 1.1014631 | E32: =INPUT_MACRO!O32 -> 11.270473 | F32: =INPUT_MACRO!P32 -> 9.0140551 | G32: =IFERROR((C32/C31-1)*100,0) -> 0.096308985 | H32: =E32-F32 -> 2.2564177 | I32: =IF(D32>=CONFIG!B7,100,IF(D32>=CONFIG!B6,65,30)) -> 30 | J32: =IF(B32>=4.5,100,IF(B32>=3.5,65,30)) -> 30 | K32: =MAX(0,100-0.35*I32-0.35*J32-0.3*ABS(G32)*15) -> 78.56661
A33: =INPUT_MACRO!A33 -> 45107 | B33: =INPUT_MACRO!C33 -> 2.9572409 | C33: =INPUT_MACRO!I33 -> 23563.826 | D33: =INPUT_MACRO!M33 -> 1.1102268 | E33: =INPUT_MACRO!O33 -> 11.050273 | F33: =INPUT_MACRO!P33 -> 8.8503398 | G33: =IFERROR((C33/C32-1)*100,0) -> 0.12562512 | H33: =E33-F33 -> 2.1999337 | I33: =IF(D33>=CONFIG!B7,100,IF(D33>=CONFIG!B6,65,30)) -> 30 | J33: =IF(B33>=4.5,100,IF(B33>=3.5,65,30)) -> 30 | K33: =MAX(0,100-0.35*I33-0.35*J33-0.3*ABS(G33)*15) -> 78.434687
A34: =INPUT_MACRO!A34 -> 45138 | B34: =INPUT_MACRO!C34 -> 2.8332049 | C34: =INPUT_MACRO!I34 -> 23600.269 | D34: =INPUT_MACRO!M34 -> 1.157506 | E34: =INPUT_MACRO!O34 -> 10.824576 | F34: =INPUT_MACRO!P34 -> 8.6944675 | G34: =IFERROR((C34/C33-1)*100,0) -> 0.15465535 | H34: =E34-F34 -> 2.1301085 | I34: =IF(D34>=CONFIG!B7,100,IF(D34>=CONFIG!B6,65,30)) -> 30 | J34: =IF(B34>=4.5,100,IF(B34>=3.5,65,30)) -> 30 | K34: =MAX(0,100-0.35*I34-0.35*J34-0.3*ABS(G34)*15) -> 78.304051
A35: =INPUT_MACRO!A35 -> 45169 | B35: =INPUT_MACRO!C35 -> 2.7124592 | C35: =INPUT_MACRO!I35 -> 23643.355 | D35: =INPUT_MACRO!M35 -> 1.2419905 | E35: =INPUT_MACRO!O35 -> 10.595636 | F35: =INPUT_MACRO!P35 -> 8.5477256 | G35: =IFERROR((C35/C34-1)*100,0) -> 0.18256789 | H35: =E35-F35 -> 2.0479099 | I35: =IF(D35>=CONFIG!B7,100,IF(D35>=CONFIG!B6,65,30)) -> 30 | J35: =IF(B35>=4.5,100,IF(B35>=3.5,65,30)) -> 30 | K35: =MAX(0,100-0.35*I35-0.35*J35-0.3*ABS(G35)*15) -> 78.178444
A36: =INPUT_MACRO!A36 -> 45199 | B36: =INPUT_MACRO!C36 -> 2.5968631 | C36: =INPUT_MACRO!I36 -> 23692.668 | D36: =INPUT_MACRO!M36 -> 1.3613389 | E36: =INPUT_MACRO!O36 -> 10.365739 | F36: =INPUT_MACRO!P36 -> 8.4113259 | G36: =IFERROR((C36/C35-1)*100,0) -> 0.20856688 | H36: =E36-F36 -> 1.9544135 | I36: =IF(D36>=CONFIG!B7,100,IF(D36>=CONFIG!B6,65,30)) -> 30 | J36: =IF(B36>=4.5,100,IF(B36>=3.5,65,30)) -> 30 | K36: =MAX(0,100-0.35*I36-0.35*J36-0.3*ABS(G36)*15) -> 78.061449
A37: =INPUT_MACRO!A37 -> 45230 | B37: =INPUT_MACRO!C37 -> 2.4882121 | C37: =INPUT_MACRO!I37 -> 23747.615 | D37: =INPUT_MACRO!M37 -> 1.5122435 | E37: =INPUT_MACRO!O37 -> 10.137185 | F37: =INPUT_MACRO!P37 -> 8.286395 | G37: =IFERROR((C37/C36-1)*100,0) -> 0.23191676 | H37: =E37-F37 -> 1.8507899 | I37: =IF(D37>=CONFIG!B7,100,IF(D37>=CONFIG!B6,65,30)) -> 30 | J37: =IF(B37>=4.5,100,IF(B37>=3.5,65,30)) -> 30 | K37: =MAX(0,100-0.35*I37-0.35*J37-0.3*ABS(G37)*15) -> 77.956375
A38: =INPUT_MACRO!A38 -> 45260 | B38: =INPUT_MACRO!C38 -> 2.3882163 | C38: =INPUT_MACRO!I38 -> 23807.45 | D38: =INPUT_MACRO!M38 -> 1.6905225 | E38: =INPUT_MACRO!O38 -> 9.9122555 | F38: =INPUT_MACRO!P38 -> 8.1739646 | G38: =IFERROR((C38/C37-1)*100,0) -> 0.25196434 | H38: =E38-F38 -> 1.7382909 | I38: =IF(D38>=CONFIG!B7,100,IF(D38>=CONFIG!B6,65,30)) -> 30 | J38: =IF(B38>=4.5,100,IF(B38>=3.5,65,30)) -> 30 | K38: =MAX(0,100-0.35*I38-0.35*J38-0.3*ABS(G38)*15) -> 77.86616
A39: =INPUT_MACRO!A39 -> 45291 | B39: =INPUT_MACRO!C39 -> 2.2984789 | C39: =INPUT_MACRO!I39 -> 23871.292 | D39: =INPUT_MACRO!M39 -> 1.8912349 | E39: =INPUT_MACRO!O39 -> 9.6931986 | F39: =INPUT_MACRO!P39 -> 8.0749633 | G39: =IFERROR((C39/C38-1)*100,0) -> 0.26815765 | H39: =E39-F39 -> 1.6182353 | I39: =IF(D39>=CONFIG!B7,100,IF(D39>=CONFIG!B6,65,30)) -> 30 | J39: =IF(B39>=4.5,100,IF(B39>=3.5,65,30)) -> 30 | K39: =MAX(0,100-0.35*I39-0.35*J39-0.3*ABS(G39)*15) -> 77.793291
A40: =INPUT_MACRO!A40 -> 45322 | B40: =INPUT_MACRO!C40 -> 2.2204765 | C40: =INPUT_MACRO!I40 -> 23938.146 | D40: =INPUT_MACRO!M40 -> 2.1088183 | E40: =INPUT_MACRO!O40 -> 9.482203 | F40: =INPUT_MACRO!P40 -> 7.9902086 | G40: =IFERROR((C40/C39-1)*100,0) -> 0.28006103 | H40: =E40-F40 -> 1.4919944 | I40: =IF(D40>=CONFIG!B7,100,IF(D40>=CONFIG!B6,65,30)) -> 30 | J40: =IF(B40>=4.5,100,IF(B40>=3.5,65,30)) -> 30 | K40: =MAX(0,100-0.35*I40-0.35*J40-0.3*ABS(G40)*15) -> 77.739725
A41: =INPUT_MACRO!A41 -> 45351 | B41: =INPUT_MACRO!C41 -> 2.1555412 | C41: =INPUT_MACRO!I41 -> 24006.936 | D41: =INPUT_MACRO!M41 -> 2.3372428 | E41: =INPUT_MACRO!O41 -> 9.2813769 | F41: =INPUT_MACRO!P41 -> 7.9204006 | G41: =IFERROR((C41/C40-1)*100,0) -> 0.28736596 | H41: =E41-F41 -> 1.3609763 | I41: =IF(D41>=CONFIG!B7,100,IF(D41>=CONFIG!B6,65,30)) -> 30 | J41: =IF(B41>=4.5,100,IF(B41>=3.5,65,30)) -> 30 | K41: =MAX(0,100-0.35*I41-0.35*J41-0.3*ABS(G41)*15) -> 77.706853
A42: =INPUT_MACRO!A42 -> 45382 | B42: =INPUT_MACRO!C42 -> 2.1048439 | C42: =INPUT_MACRO!I42 -> 24076.532 | D42: =INPUT_MACRO!M42 -> 2.5701778 | E42: =INPUT_MACRO!O42 -> 9.0927269 | F42: =INPUT_MACRO!P42 -> 7.8661158 | G42: =IFERROR((C42/C41-1)*100,0) -> 0.28989765 | H42: =E42-F42 -> 1.2266111 | I42: =IF(D42>=CONFIG!B7,100,IF(D42>=CONFIG!B6,65,30)) -> 30 | J42: =IF(B42>=4.5,100,IF(B42>=3.5,65,30)) -> 30 | K42: =MAX(0,100-0.35*I42-0.35*J42-0.3*ABS(G42)*15) -> 77.695461
A43: =INPUT_MACRO!A43 -> 45412 | B43: =INPUT_MACRO!C43 -> 2.0693797 | C43: =INPUT_MACRO!I43 -> 24145.78 | D43: =INPUT_MACRO!M43 -> 3.801168 | E43: =INPUT_MACRO!O43 -> 8.9181378 | F43: =INPUT_MACRO!P43 -> 7.8278025 | G43: =IFERROR((C43/C42-1)*100,0) -> 0.28761719 | H43: =E43-F43 -> 1.0903354 | I43: =IF(D43>=CONFIG!B7,100,IF(D43>=CONFIG!B6,65,30)) -> 30 | J43: =IF(B43>=4.5,100,IF(B43>=3.5,65,30)) -> 30 | K43: =MAX(0,100-0.35*I43-0.35*J43-0.3*ABS(G43)*15) -> 77.705723
A44: =INPUT_MACRO!A44 -> 45443 | B44: =INPUT_MACRO!C44 -> 2.049956 | C44: =INPUT_MACRO!I44 -> 24213.538 | D44: =INPUT_MACRO!M44 -> 4.0238117 | E44: =INPUT_MACRO!O44 -> 8.7593543 | F44: =INPUT_MACRO!P44 -> 7.8057771 | G44: =IFERROR((C44/C43-1)*100,0) -> 0.28061968 | H44: =E44-F44 -> 0.95357719 | I44: =IF(D44>=CONFIG!B7,100,IF(D44>=CONFIG!B6,65,30)) -> 30 | J44: =IF(B44>=4.5,100,IF(B44>=3.5,65,30)) -> 30 | K44: =MAX(0,100-0.35*I44-0.35*J44-0.3*ABS(G44)*15) -> 77.737211
A45: =INPUT_MACRO!A45 -> 45473 | B45: =INPUT_MACRO!C45 -> 2.0471824 | C45: =INPUT_MACRO!I45 -> 24278.703 | D45: =INPUT_MACRO!M45 -> 4.2319388 | E45: =INPUT_MACRO!O45 -> 8.6179626 | F45: =INPUT_MACRO!P45 -> 7.8002215 | G45: =IFERROR((C45/C44-1)*100,0) -> 0.26912857 | H45: =E45-F45 -> 0.81774112 | I45: =IF(D45>=CONFIG!B7,100,IF(D45>=CONFIG!B6,65,30)) -> 30 | J45: =IF(B45>=4.5,100,IF(B45>=3.5,65,30)) -> 30 | K45: =MAX(0,100-0.35*I45-0.35*J45-0.3*ABS(G45)*15) -> 77.788921
A46: =INPUT_MACRO!A46 -> 45504 | B46: =INPUT_MACRO!C46 -> 2.0614631 | C46: =INPUT_MACRO!I46 -> 24340.247 | D46: =INPUT_MACRO!M46 -> 4.4197812 | E46: =INPUT_MACRO!O46 -> 8.4953757 | F46: =INPUT_MACRO!P46 -> 7.8111817 | G46: =IFERROR((C46/C45-1)*100,0) -> 0.25348675 | H46: =E46-F46 -> 0.68419403 | I46: =IF(D46>=CONFIG!B7,100,IF(D46>=CONFIG!B6,65,30)) -> 30 | J46: =IF(B46>=4.5,100,IF(B46>=3.5,65,30)) -> 30 | K46: =MAX(0,100-0.35*I46-0.35*J46-0.3*ABS(G46)*15) -> 77.85931
A47: =INPUT_MACRO!A47 -> 45535 | B47: =INPUT_MACRO!C47 -> 2.0929919 | C47: =INPUT_MACRO!I47 -> 24397.238 | D47: =INPUT_MACRO!M47 -> 4.5821333 | E47: =INPUT_MACRO!O47 -> 8.3928183 | F47: =INPUT_MACRO!P47 -> 7.8385671 | G47: =IFERROR((C47/C46-1)*100,0) -> 0.23414487 | H47: =E47-F47 -> 0.55425129 | I47: =IF(D47>=CONFIG!B7,100,IF(D47>=CONFIG!B6,65,30)) -> 65 | J47: =IF(B47>=4.5,100,IF(B47>=3.5,65,30)) -> 30 | K47: =MAX(0,100-0.35*I47-0.35*J47-0.3*ABS(G47)*15) -> 65.696348
A48: =INPUT_MACRO!A48 -> 45565 | B48: =INPUT_MACRO!C48 -> 2.14175 | C48: =INPUT_MACRO!I48 -> 24448.874 | D48: =INPUT_MACRO!M48 -> 4.7144956 | E48: =INPUT_MACRO!O48 -> 8.3113152 | F48: =INPUT_MACRO!P48 -> 7.8821515 | G48: =IFERROR((C48/C47-1)*100,0) -> 0.21164743 | H48: =E48-F48 -> 0.42916378 | I48: =IF(D48>=CONFIG!B7,100,IF(D48>=CONFIG!B6,65,30)) -> 65 | J48: =IF(B48>=4.5,100,IF(B48>=3.5,65,30)) -> 30 | K48: =MAX(0,100-0.35*I48-0.35*J48-0.3*ABS(G48)*15) -> 65.797587
A49: =INPUT_MACRO!A49 -> 45596 | B49: =INPUT_MACRO!C49 -> 2.207506 | C49: =INPUT_MACRO!I49 -> 24494.5 | D49: =INPUT_MACRO!M49 -> 4.8132 | E49: =INPUT_MACRO!O49 -> 8.2516807 | F49: =INPUT_MACRO!P49 -> 7.9415749 | G49: =IFERROR((C49/C48-1)*100,0) -> 0.18661709 | H49: =E49-F49 -> 0.31010581 | I49: =IF(D49>=CONFIG!B7,100,IF(D49>=CONFIG!B6,65,30)) -> 65 | J49: =IF(B49>=4.5,100,IF(B49>=3.5,65,30)) -> 30 | K49: =MAX(0,100-0.35*I49-0.35*J49-0.3*ABS(G49)*15) -> 65.910223
A50: =INPUT_MACRO!A50 -> 45626 | B50: =INPUT_MACRO!C50 -> 2.289819 | C50: =INPUT_MACRO!I50 -> 24533.627 | D50: =INPUT_MACRO!M50 -> 4.8755109 | E50: =INPUT_MACRO!O50 -> 8.2145107 | F50: =INPUT_MACRO!P50 -> 8.0163467 | G50: =IFERROR((C50/C49-1)*100,0) -> 0.15973771 | H50: =E50-F50 -> 0.19816399 | I50: =IF(D50>=CONFIG!B7,100,IF(D50>=CONFIG!B6,65,30)) -> 65 | J50: =IF(B50>=4.5,100,IF(B50>=3.5,65,30)) -> 30 | K50: =MAX(0,100-0.35*I50-0.35*J50-0.3*ABS(G50)*15) -> 66.03118
A51: =INPUT_MACRO!A51 -> 45657 | B51: =INPUT_MACRO!C51 -> 2.3880437 | C51: =INPUT_MACRO!I51 -> 24565.947 | D51: =INPUT_MACRO!M51 -> 4.8997016 | E51: =INPUT_MACRO!O51 -> 8.2001765 | F51: =INPUT_MACRO!P51 -> 8.1058493 | G51: =IFERROR((C51/C50-1)*100,0) -> 0.13173658 | H51: =E51-F51 -> 0.09432724 | I51: =IF(D51>=CONFIG!B7,100,IF(D51>=CONFIG!B6,65,30)) -> 65 | J51: =IF(B51>=4.5,100,IF(B51>=3.5,65,30)) -> 30 | K51: =MAX(0,100-0.35*I51-0.35*J51-0.3*ABS(G51)*15) -> 66.157185
A52: =INPUT_MACRO!A52 -> 45688 | B52: =INPUT_MACRO!C52 -> 2.5013389 | C52: =INPUT_MACRO!I52 -> 24591.34 | D52: =INPUT_MACRO!M52 -> 4.8851015 | E52: =INPUT_MACRO!O52 -> 8.2088214 | F52: =INPUT_MACRO!P52 -> 8.2093434 | G52: =IFERROR((C52/C51-1)*100,0) -> 0.10336607 | H52: =E52-F52 -> -0.00052204028 | I52: =IF(D52>=CONFIG!B7,100,IF(D52>=CONFIG!B6,65,30)) -> 65 | J52: =IF(B52>=4.5,100,IF(B52>=3.5,65,30)) -> 30 | K52: =MAX(0,100-0.35*I52-0.35*J52-0.3*ABS(G52)*15) -> 66.284853
A53: =INPUT_MACRO!A53 -> 45716 | B53: =INPUT_MACRO!C53 -> 2.6286771 | C53: =INPUT_MACRO!I53 -> 24609.878 | D53: =INPUT_MACRO!M53 -> 4.8321155 | E53: =INPUT_MACRO!O53 -> 8.240359 | F53: =INPUT_MACRO!P53 -> 8.3259745 | G53: =IFERROR((C53/C52-1)*100,0) -> 0.075385075 | H53: =E53-F53 -> -0.085615492 | I53: =IF(D53>=CONFIG!B7,100,IF(D53>=CONFIG!B6,65,30)) -> 65 | J53: =IF(B53>=4.5,100,IF(B53>=3.5,65,30)) -> 30 | K53: =MAX(0,100-0.35*I53-0.35*J53-0.3*ABS(G53)*15) -> 66.410767
A54: =INPUT_MACRO!A54 -> 45747 | B54: =INPUT_MACRO!C54 -> 2.7688579 | C54: =INPUT_MACRO!I54 -> 24621.824 | D54: =INPUT_MACRO!M54 -> 4.7422118 | E54: =INPUT_MACRO!O54 -> 8.2944742 | F54: =INPUT_MACRO!P54 -> 8.4547792 | G54: =IFERROR((C54/C53-1)*100,0) -> 0.048540532 | H54: =E54-F54 -> -0.160305 | I54: =IF(D54>=CONFIG!B7,100,IF(D54>=CONFIG!B6,65,30)) -> 65 | J54: =IF(B54>=4.5,100,IF(B54>=3.5,65,30)) -> 30 | K54: =MAX(0,100-0.35*I54-0.35*J54-0.3*ABS(G54)*15) -> 66.531568
A55: =INPUT_MACRO!A55 -> 45777 | B55: =INPUT_MACRO!C55 -> 2.9205225 | C55: =INPUT_MACRO!I55 -> 24627.622 | D55: =INPUT_MACRO!M55 -> 4.617882 | E55: =INPUT_MACRO!O55 -> 8.3706262 | F55: =INPUT_MACRO!P55 -> 8.5946937 | G55: =IFERROR((C55/C54-1)*100,0) -> 0.023549235 | H55: =E55-F55 -> -0.2240675 | I55: =IF(D55>=CONFIG!B7,100,IF(D55>=CONFIG!B6,65,30)) -> 65 | J55: =IF(B55>=4.5,100,IF(B55>=3.5,65,30)) -> 30 | K55: =MAX(0,100-0.35*I55-0.35*J55-0.3*ABS(G55)*15) -> 66.644028
A56: =INPUT_MACRO!A56 -> 45808 | B56: =INPUT_MACRO!C56 -> 3.0821703 | C56: =INPUT_MACRO!I56 -> 24627.888 | D56: =INPUT_MACRO!M56 -> 4.4625717 | E56: =INPUT_MACRO!O56 -> 8.4680543 | F56: =INPUT_MACRO!P56 -> 8.7445626 | G56: =IFERROR((C56/C55-1)*100,0) -> 0.0010801921 | H56: =E56-F56 -> -0.27650834 | I56: =IF(D56>=CONFIG!B7,100,IF(D56>=CONFIG!B6,65,30)) -> 30 | J56: =IF(B56>=4.5,100,IF(B56>=3.5,65,30)) -> 30 | K56: =MAX(0,100-0.35*I56-0.35*J56-0.3*ABS(G56)*15) -> 78.995139
A57: =INPUT_MACRO!A57 -> 45838 | B57: =INPUT_MACRO!C57 -> 3.2521778 | C57: =INPUT_MACRO!I57 -> 24623.39 | D57: =INPUT_MACRO!M57 -> 4.2805852 | E57: =INPUT_MACRO!O57 -> 8.5857849 | F57: =INPUT_MACRO!P57 -> 8.9031482 | G57: =IFERROR((C57/C56-1)*100,0) -> -0.018262197 | H57: =E57-F57 -> -0.31736328 | I57: =IF(D57>=CONFIG!B7,100,IF(D57>=CONFIG!B6,65,30)) -> 30 | J57: =IF(B57>=4.5,100,IF(B57>=3.5,65,30)) -> 30 | K57: =MAX(0,100-0.35*I57-0.35*J57-0.3*ABS(G57)*15) -> 78.91782
A58: =INPUT_MACRO!A58 -> 45869 | B58: =INPUT_MACRO!C58 -> 3.4288183 | C58: =INPUT_MACRO!I58 -> 24615.03 | D58: =INPUT_MACRO!M58 -> 4.0769659 | E58: =INPUT_MACRO!O58 -> 8.7226417 | F58: =INPUT_MACRO!P58 -> 9.0691406 | G58: =IFERROR((C58/C57-1)*100,0) -> -0.033953851 | H58: =E58-F58 -> -0.3464989 | I58: =IF(D58>=CONFIG!B7,100,IF(D58>=CONFIG!B6,65,30)) -> 30 | J58: =IF(B58>=4.5,100,IF(B58>=3.5,65,30)) -> 30 | K58: =MAX(0,100-0.35*I58-0.35*J58-0.3*ABS(G58)*15) -> 78.847208
A59: =INPUT_MACRO!A59 -> 45900 | B59: =INPUT_MACRO!C59 -> 3.6102832 | C59: =INPUT_MACRO!I59 -> 24603.814 | D59: =INPUT_MACRO!M59 -> 3.8573568 | E59: =INPUT_MACRO!O59 -> 8.8772573 | F59: =INPUT_MACRO!P59 -> 9.241169 | G59: =IFERROR((C59/C58-1)*100,0) -> -0.045565268 | H59: =E59-F59 -> -0.36391175 | I59: =IF(D59>=CONFIG!B7,100,IF(D59>=CONFIG!B6,65,30)) -> 30 | J59: =IF(B59>=4.5,100,IF(B59>=3.5,65,30)) -> 65 | K59: =MAX(0,100-0.35*I59-0.35*J59-0.3*ABS(G59)*15) -> 66.544956
A60: =INPUT_MACRO!A60 -> 45930 | B60: =INPUT_MACRO!C60 -> 3.7947045 | C60: =INPUT_MACRO!I60 -> 24590.829 | D60: =INPUT_MACRO!M60 -> 3.6278441 | E60: =INPUT_MACRO!O60 -> 9.0480867 | F60: =INPUT_MACRO!P60 -> 9.4178127 | G60: =IFERROR((C60/C59-1)*100,0) -> -0.052773965 | H60: =E60-F60 -> -0.36972595 | I60: =IF(D60>=CONFIG!B7,100,IF(D60>=CONFIG!B6,65,30)) -> 30 | J60: =IF(B60>=4.5,100,IF(B60>=3.5,65,30)) -> 65 | K60: =MAX(0,100-0.35*I60-0.35*J60-0.3*ABS(G60)*15) -> 66.512517
A61: =INPUT_MACRO!A61 -> 45961 | B61: =INPUT_MACRO!C61 -> 3.9801778 | C61: =INPUT_MACRO!I61 -> 24577.212 | D61: =INPUT_MACRO!M61 -> 3.3947884 | E61: =INPUT_MACRO!O61 -> 9.2334233 | F61: =INPUT_MACRO!P61 -> 9.5976128 | G61: =IFERROR((C61/C60-1)*100,0) -> -0.055374664 | H61: =E61-F61 -> -0.36418951 | I61: =IF(D61>=CONFIG!B7,100,IF(D61>=CONFIG!B6,65,30)) -> 30 | J61: =IF(B61>=4.5,100,IF(B61>=3.5,65,30)) -> 65 | K61: =MAX(0,100-0.35*I61-0.35*J61-0.3*ABS(G61)*15) -> 66.500814
A62: =INPUT_MACRO!A62 -> 45991 | B62: =INPUT_MACRO!C62 -> 4.1647856 | C62: =INPUT_MACRO!I62 -> 24564.116 | D62: =INPUT_MACRO!M62 -> 3.1646485 | E62: =INPUT_MACRO!O62 -> 9.431415 | F62: =INPUT_MACRO!P62 -> 9.7790843 | G62: =IFERROR((C62/C61-1)*100,0) -> -0.053286813 | H62: =E62-F62 -> -0.34766933 | I62: =IF(D62>=CONFIG!B7,100,IF(D62>=CONFIG!B6,65,30)) -> 30 | J62: =IF(B62>=4.5,100,IF(B62>=3.5,65,30)) -> 65 | K62: =MAX(0,100-0.35*I62-0.35*J62-0.3*ABS(G62)*15) -> 66.510209
A63: =INPUT_MACRO!A63 -> 46022 | B63: =INPUT_MACRO!C63 -> 4.3466211 | C63: =INPUT_MACRO!I63 -> 24552.679 | D63: =INPUT_MACRO!M63 -> 2.9438024 | E63: =INPUT_MACRO!O63 -> 9.6400837 | F63: =INPUT_MACRO!P63 -> 9.9607286 | G63: =IFERROR((C63/C62-1)*100,0) -> -0.046559015 | H63: =E63-F63 -> -0.32064493 | I63: =IF(D63>=CONFIG!B7,100,IF(D63>=CONFIG!B6,65,30)) -> 30 | J63: =IF(B63>=4.5,100,IF(B63>=3.5,65,30)) -> 65 | K63: =MAX(0,100-0.35*I63-0.35*J63-0.3*ABS(G63)*15) -> 66.540484
A64: =INPUT_MACRO!A64 -> 46053 | B64: =INPUT_MACRO!C64 -> 4.5238117 | C64: =INPUT_MACRO!I64 -> 24543.995 | D64: =INPUT_MACRO!M64 -> 2.7383704 | E64: =INPUT_MACRO!O64 -> 9.8573444 | F64: =INPUT_MACRO!P64 -> 10.141045 | G64: =IFERROR((C64/C63-1)*100,0) -> -0.035369965 | H64: =E64-F64 -> -0.28370111 | I64: =IF(D64>=CONFIG!B7,100,IF(D64>=CONFIG!B6,65,30)) -> 30 | J64: =IF(B64>=4.5,100,IF(B64>=3.5,65,30)) -> 100 | K64: =MAX(0,100-0.35*I64-0.35*J64-0.3*ABS(G64)*15) -> 54.340835
A65: =INPUT_MACRO!A65 -> 46081 | B65: =INPUT_MACRO!C65 -> 4.6945422 | C65: =INPUT_MACRO!I65 -> 24539.08 | D65: =INPUT_MACRO!M65 -> 2.554046 | E65: =INPUT_MACRO!O65 -> 10.081026 | F65: =INPUT_MACRO!P65 -> 10.318546 | G65: =IFERROR((C65/C64-1)*100,0) -> -0.020025619 | H65: =E65-F65 -> -0.23751947 | I65: =IF(D65>=CONFIG!B7,100,IF(D65>=CONFIG!B6,65,30)) -> 30 | J65: =IF(B65>=4.5,100,IF(B65>=3.5,65,30)) -> 100 | K65: =MAX(0,100-0.35*I65-0.35*J65-0.3*ABS(G65)*15) -> 54.409885
A66: =INPUT_MACRO!A66 -> 46112 | B66: =INPUT_MACRO!C66 -> 4.8570769 | C66: =INPUT_MACRO!I66 -> 24538.846 | D66: =INPUT_MACRO!M66 -> 2.3959372 | E66: =INPUT_MACRO!O66 -> 10.308894 | F66: =INPUT_MACRO!P66 -> 10.491763 | G66: =IFERROR((C66/C65-1)*100,0) -> -0.00095238308 | H66: =E66-F66 -> -0.18286904 | I66: =IF(D66>=CONFIG!B7,100,IF(D66>=CONFIG!B6,65,30)) -> 30 | J66: =IF(B66>=4.5,100,IF(B66>=3.5,65,30)) -> 100 | K66: =MAX(0,100-0.35*I66-0.35*J66-0.3*ABS(G66)*15) -> 54.495714
A67: =INPUT_MACRO!A67 -> 46142 | B67: =INPUT_MACRO!C67 -> 5.0097812 | C67: =INPUT_MACRO!I67 -> 24544.076 | D67: =INPUT_MACRO!M67 -> 2.2684259 | E67: =INPUT_MACRO!O67 -> 10.538672 | F67: =INPUT_MACRO!P67 -> 10.659268 | G67: =IFERROR((C67/C66-1)*100,0) -> 0.021313678 | H67: =E67-F67 -> -0.12059602 | I67: =IF(D67>=CONFIG!B7,100,IF(D67>=CONFIG!B6,65,30)) -> 30 | J67: =IF(B67>=4.5,100,IF(B67>=3.5,65,30)) -> 100 | K67: =MAX(0,100-0.35*I67-0.35*J67-0.3*ABS(G67)*15) -> 54.404088

Sheet PROC_ABBANK
A1: PROC_ABBANK - ABBank Scorecard | B1: PROC_ABBANK - ABBank Scorecard | C1: PROC_ABBANK - ABBank Scorecard | D1: PROC_ABBANK - ABBank Scorecard | E1: PROC_ABBANK - ABBank Scorecard | F1: PROC_ABBANK - ABBank Scorecard | G1: PROC_ABBANK - ABBank Scorecard | H1: PROC_ABBANK - ABBank Scorecard | I1: PROC_ABBANK - ABBank Scorecard | J1: PROC_ABBANK - ABBank Scorecard | K1: PROC_ABBANK - ABBank Scorecard
A3: date | B3: loan_growth | C3: deposit_growth | D3: casa | E3: nim | F3: ldr | G3: npl | H3: growth_score | I3: funding_score | J3: asset_quality_score | K3: abbank_score
A4: =INPUT_ABBANK!A4 -> 44227 | B4: =INPUT_ABBANK!C4 -> 9 | C4: =INPUT_ABBANK!E4 -> 10.482942 | D4: =INPUT_ABBANK!F4 -> 14 | E4: =INPUT_ABBANK!G4 -> 3.05 | F4: =INPUT_ABBANK!J4 -> 87.755102 | G4: =INPUT_ABBANK!K4 -> 2 | H4: =MIN(100,MAX(0,50+B4*3)) -> 77 | I4: =MAX(0,100-(MAX(0,F4-80)*3)+D4) -> 90.734694 | J4: =MAX(0,100-G4*20) -> 60 | K4: =0.3*H4+0.4*I4+0.3*J4 -> 77.393878
A5: =INPUT_ABBANK!A5 -> 44255 | B5: =INPUT_ABBANK!C5 -> 9.2439418 | C5: =INPUT_ABBANK!E5 -> 10.604535 | D5: =INPUT_ABBANK!F5 -> 14.199667 | E5: =INPUT_ABBANK!G5 -> 3.0855929 | F5: =INPUT_ABBANK!J5 -> 88.046896 | G5: =INPUT_ABBANK!K5 -> 2.0436362 | H5: =MIN(100,MAX(0,50+B5*3)) -> 77.731825 | I5: =MAX(0,100-(MAX(0,F5-80)*3)+D5) -> 90.058977 | J5: =MAX(0,100-G5*20) -> 59.127277 | K5: =0.3*H5+0.4*I5+0.3*J5 -> 77.081322
A6: =INPUT_ABBANK!A6 -> 44286 | B6: =INPUT_ABBANK!C6 -> 9.484875 | C6: =INPUT_ABBANK!E6 -> 10.697969 | D6: =INPUT_ABBANK!F6 -> 14.397339 | E6: =INPUT_ABBANK!G6 -> 3.1204607 | F6: =INPUT_ABBANK!J6 -> 88.325964 | G6: =INPUT_ABBANK!K6 -> 2.0865914 | H6: =MIN(100,MAX(0,50+B6*3)) -> 78.454625 | I6: =MAX(0,100-(MAX(0,F6-80)*3)+D6) -> 89.419446 | J6: =MAX(0,100-G6*20) -> 58.268172 | K6: =0.3*H6+0.4*I6+0.3*J6 -> 76.784618
A7: =INPUT_ABBANK!A7 -> 44316 | B7: =INPUT_ABBANK!C7 -> 9.7198283 | C7: =INPUT_ABBANK!E7 -> 10.761786 | D7: =INPUT_ABBANK!F7 -> 14.59104 | E7: =INPUT_ABBANK!G7 -> 3.153893 | F7: =INPUT_ABBANK!J7 -> 88.586125 | G7: =INPUT_ABBANK!K7 -> 2.1281954 | H7: =MIN(100,MAX(0,50+B7*3)) -> 79.159485 | I7: =MAX(0,100-(MAX(0,F7-80)*3)+D7) -> 88.832664 | J7: =MAX(0,100-G7*20) -> 57.436092 | K7: =0.3*H7+0.4*I7+0.3*J7 -> 76.511739
A8: =INPUT_ABBANK!A8 -> 44347 | B8: =INPUT_ABBANK!C8 -> 9.945904 | C8: =INPUT_ABBANK!E8 -> 10.79499 | D8: =INPUT_ABBANK!F8 -> 14.778837 | E8: =INPUT_ABBANK!G8 -> 3.1852086 | F8: =INPUT_ABBANK!J8 -> 88.822127 | G8: =INPUT_ABBANK!K8 -> 2.1677989 | H8: =MIN(100,MAX(0,50+B8*3)) -> 79.837712 | I8: =MAX(0,100-(MAX(0,F8-80)*3)+D8) -> 88.312455 | J8: =MAX(0,100-G8*20) -> 56.644021 | K8: =0.3*H8+0.4*I8+0.3*J8 -> 76.269502
A9: =INPUT_ABBANK!A9 -> 44377 | B9: =INPUT_ABBANK!C9 -> 10.160314 | C9: =INPUT_ABBANK!E9 -> 10.797063 | D9: =INPUT_ABBANK!F9 -> 14.958851 | E9: =INPUT_ABBANK!G9 -> 3.2137695 | F9: =INPUT_ABBANK!J9 -> 89.029865 | G9: =INPUT_ABBANK!K9 -> 2.204784 | H9: =MIN(100,MAX(0,50+B9*3)) -> 80.480942 | I9: =MAX(0,100-(MAX(0,F9-80)*3)+D9) -> 87.869256 | J9: =MAX(0,100-G9*20) -> 55.904319 | K9: =0.3*H9+0.4*I9+0.3*J9 -> 76.063281
A10: =INPUT_ABBANK!A10 -> 44408 | B10: =INPUT_ABBANK!C10 -> 10.360414 | C10: =INPUT_ABBANK!E10 -> 10.767972 | D10: =INPUT_ABBANK!F10 -> 15.129285 | E10: =INPUT_ABBANK!G10 -> 3.2389938 | F10: =INPUT_ABBANK!J10 -> 89.206547 | G10: =INPUT_ABBANK!K10 -> 2.2385736 | H10: =MIN(100,MAX(0,50+B10*3)) -> 81.081241 | I10: =MAX(0,100-(MAX(0,F10-80)*3)+D10) -> 87.509645 | J10: =MAX(0,100-G10*20) -> 55.228529 | K10: =0.3*H10+0.4*I10+0.3*J10 -> 75.896789
A11: =INPUT_ABBANK!A11 -> 44439 | B11: =INPUT_ABBANK!C11 -> 10.543735 | C11: =INPUT_ABBANK!E11 -> 10.708172 | D11: =INPUT_ABBANK!F11 -> 15.288435 | E11: =INPUT_ABBANK!G11 -> 3.2603677 | F11: =INPUT_ABBANK!J11 -> 89.350799 | G11: =INPUT_ABBANK!K11 -> 2.2686402 | H11: =MIN(100,MAX(0,50+B11*3)) -> 81.631206 | I11: =MAX(0,100-(MAX(0,F11-80)*3)+D11) -> 87.236038 | J11: =MAX(0,100-G11*20) -> 54.627195 | K11: =0.3*H11+0.4*I11+0.3*J11 -> 75.771936
A12: =INPUT_ABBANK!A12 -> 44469 | B12: =INPUT_ABBANK!C12 -> 10.708018 | C12: =INPUT_ABBANK!E12 -> 10.618595 | D12: =INPUT_ABBANK!F12 -> 15.434712 | E12: =INPUT_ABBANK!G12 -> 3.2774557 | F12: =INPUT_ABBANK!J12 -> 89.462715 | G12: =INPUT_ABBANK!K12 -> 2.2945148 | H12: =MIN(100,MAX(0,50+B12*3)) -> 82.124055 | I12: =MAX(0,100-(MAX(0,F12-80)*3)+D12) -> 87.046568 | J12: =MAX(0,100-G12*20) -> 54.109703 | K12: =0.3*H12+0.4*I12+0.3*J12 -> 75.688754
A13: =INPUT_ABBANK!A13 -> 44500 | B13: =INPUT_ABBANK!C13 -> 10.851236 | C13: =INPUT_ABBANK!E13 -> 10.50064 | D13: =INPUT_ABBANK!F13 -> 15.566654 | E13: =INPUT_ABBANK!G13 -> 3.2899096 | F13: =INPUT_ABBANK!J13 -> 89.543837 | G13: =INPUT_ABBANK!K13 -> 2.3157937 | H13: =MIN(100,MAX(0,50+B13*3)) -> 82.553708 | I13: =MAX(0,100-(MAX(0,F13-80)*3)+D13) -> 86.935144 | J13: =MAX(0,100-G13*20) -> 53.684127 | K13: =0.3*H13+0.4*I13+0.3*J13 -> 75.645408
A14: =INPUT_ABBANK!A14 -> 44530 | B14: =INPUT_ABBANK!C14 -> 10.971623 | C14: =INPUT_ABBANK!E14 -> 10.356146 | D14: =INPUT_ABBANK!F14 -> 15.682942 | E14: =INPUT_ABBANK!G14 -> 3.2974758 | F14: =INPUT_ABBANK!J14 -> 89.597087 | G14: =INPUT_ABBANK!K14 -> 2.3321446 | H14: =MIN(100,MAX(0,50+B14*3)) -> 82.914869 | I14: =MAX(0,100-(MAX(0,F14-80)*3)+D14) -> 86.89168 | J14: =MAX(0,100-G14*20) -> 53.357108 | K14: =0.3*H14+0.4*I14+0.3*J14 -> 75.638265
A15: =INPUT_ABBANK!A15 -> 44561 | B15: =INPUT_ABBANK!C15 -> 11.067694 | C15: =INPUT_ABBANK!E15 -> 10.18737 | D15: =INPUT_ABBANK!F15 -> 15.782415 | E15: =INPUT_ABBANK!G15 -> 3.3 | F15: =INPUT_ABBANK!J15 -> 89.626645 | G15: =INPUT_ABBANK!K15 -> 2.3433126 | H15: =MIN(100,MAX(0,50+B15*3)) -> 83.203081 | I15: =MAX(0,100-(MAX(0,F15-80)*3)+D15) -> 86.902481 | J15: =MAX(0,100-G15*20) -> 53.133749 | K15: =0.3*H15+0.4*I15+0.3*J15 -> 75.662041
... A67: =INPUT_ABBANK!A67 -> 46142 | B67: =INPUT_ABBANK!C67 -> 10.445371 | C67: =INPUT_ABBANK!E67 -> 9.8449958 | D67: =INPUT_ABBANK!F67 -> 14.033628 | E67: =INPUT_ABBANK!G67 -> 3.1530296 | F67: =INPUT_ABBANK!J67 -> 95.561516 | G67: =INPUT_ABBANK!K67 -> 2.3499227 | H67: =MIN(100,MAX(0,50+B67*3)) -> 81.336112 | I67: =MAX(0,100-(MAX(0,F67-80)*3)+D67) -> 67.349078 | J67: =MAX(0,100-G67*20) -> 53.001546 | K67: =0.3*H67+0.4*I67+0.3*J67 -> 67.240929

Sheet PROC_TREASURY
A1: PROC_TREASURY - Duration, DV01 & Stress | B1: PROC_TREASURY - Duration, DV01 & Stress | C1: PROC_TREASURY - Duration, DV01 & Stress | D1: PROC_TREASURY - Duration, DV01 & Stress | E1: PROC_TREASURY - Duration, DV01 & Stress | F1: PROC_TREASURY - Duration, DV01 & Stress | G1: PROC_TREASURY - Duration, DV01 & Stress | H1: PROC_TREASURY - Duration, DV01 & Stress | I1: PROC_TREASURY - Duration, DV01 & Stress | J1: PROC_TREASURY - Duration, DV01 & Stress
A3: date | B3: portfolio_size | C3: duration | D3: dv01 | E3: stress_loss_100bps | F3: stress_loss_200bps | G3: loss_100bps_pct_capital | H3: loss_200bps_pct_capital | I3: treasury_risk_score | J3: risk_level
A4: =INPUT_TREASURY!A4 -> 44227 | B4: =INPUT_TREASURY!B4 -> 50000 | C4: =INPUT_TREASURY!C4 -> 2.1 | D4: =INPUT_TREASURY!D4 -> 4.7 | E4: =D4*100 -> 470 | F4: =D4*200 -> 940 | G4: =E4/CONFIG!B4*100 -> 0.94 | H4: =F4/CONFIG!B4*100 -> 1.88 | I4: =MAX(0,100-H4*10-C4*8) -> 64.4 | J4: =IF(H4>=CONFIG!B15,"Đỏ",IF(H4>=CONFIG!B14,"Vàng","Xanh")) -> Xanh
A5: =INPUT_TREASURY!A5 -> 44255 | B5: =INPUT_TREASURY!B5 -> 50000 | C5: =INPUT_TREASURY!C5 -> 2.1436362 | D5: =INPUT_TREASURY!D5 -> 4.7798667 | E5: =D5*100 -> 477.98667 | F5: =D5*200 -> 955.97335 | G5: =E5/CONFIG!B4*100 -> 0.95597335 | H5: =F5/CONFIG!B4*100 -> 1.9119467 | I5: =MAX(0,100-H5*10-C5*8) -> 63.731444 | J5: =IF(H5>=CONFIG!B15,"Đỏ",IF(H5>=CONFIG!B14,"Vàng","Xanh")) -> Xanh
A6: =INPUT_TREASURY!A6 -> 44286 | B6: =INPUT_TREASURY!B6 -> 50000 | C6: =INPUT_TREASURY!C6 -> 2.1865914 | D6: =INPUT_TREASURY!D6 -> 4.8589355 | E6: =D6*100 -> 485.89355 | F6: =D6*200 -> 971.78709 | G6: =E6/CONFIG!B4*100 -> 0.97178709 | H6: =F6/CONFIG!B4*100 -> 1.9435742 | I6: =MAX(0,100-H6*10-C6*8) -> 63.071527 | J6: =IF(H6>=CONFIG!B15,"Đỏ",IF(H6>=CONFIG!B14,"Vàng","Xanh")) -> Xanh
A7: =INPUT_TREASURY!A7 -> 44316 | B7: =INPUT_TREASURY!B7 -> 50000 | C7: =INPUT_TREASURY!C7 -> 2.2281954 | D7: =INPUT_TREASURY!D7 -> 4.9364162 | E7: =D7*100 -> 493.64162 | F7: =D7*200 -> 987.28323 | G7: =E7/CONFIG!B4*100 -> 0.98728323 | H7: =F7/CONFIG!B4*100 -> 1.9745665 | I7: =MAX(0,100-H7*10-C7*8) -> 62.428772 | J7: =IF(H7>=CONFIG!B15,"Đỏ",IF(H7>=CONFIG!B14,"Vàng","Xanh")) -> Xanh
A8: =INPUT_TREASURY!A8 -> 44347 | B8: =INPUT_TREASURY!B8 -> 50000 | C8: =INPUT_TREASURY!C8 -> 2.2677989 | D8: =INPUT_TREASURY!D8 -> 5.0115347 | E8: =D8*100 -> 501.15347 | F8: =D8*200 -> 1002.3069 | G8: =E8/CONFIG!B4*100 -> 1.0023069 | H8: =F8/CONFIG!B4*100 -> 2.0046139 | I8: =MAX(0,100-H8*10-C8*8) -> 61.81147 | J8: =IF(H8>=CONFIG!B15,"Đỏ",IF(H8>=CONFIG!B14,"Vàng","Xanh")) -> Xanh
A9: =INPUT_TREASURY!A9 -> 44377 | B9: =INPUT_TREASURY!B9 -> 50000 | C9: =INPUT_TREASURY!C9 -> 2.304784 | D9: =INPUT_TREASURY!D9 -> 5.0835404 | E9: =D9*100 -> 508.35404 | F9: =D9*200 -> 1016.7081 | G9: =E9/CONFIG!B4*100 -> 1.0167081 | H9: =F9/CONFIG!B4*100 -> 2.0334162 | I9: =MAX(0,100-H9*10-C9*8) -> 61.227566 | J9: =IF(H9>=CONFIG!B15,"Đỏ",IF(H9>=CONFIG!B14,"Vàng","Xanh")) -> Xanh
A10: =INPUT_TREASURY!A10 -> 44408 | B10: =INPUT_TREASURY!B10 -> 50000 | C10: =INPUT_TREASURY!C10 -> 2.3385736 | D10: =INPUT_TREASURY!D10 -> 5.151714 | E10: =D10*100 -> 515.1714 | F10: =D10*200 -> 1030.3428 | G10: =E10/CONFIG!B4*100 -> 1.0303428 | H10: =F10/CONFIG!B4*100 -> 2.0606856 | I10: =MAX(0,100-H10*10-C10*8) -> 60.684556 | J10: =IF(H10>=CONFIG!B15,"Đỏ",IF(H10>=CONFIG!B14,"Vàng","Xanh")) -> Xanh
A11: =INPUT_TREASURY!A11 -> 44439 | B11: =INPUT_TREASURY!B11 -> 50000 | C11: =INPUT_TREASURY!C11 -> 2.3686402 | D11: =INPUT_TREASURY!D11 -> 5.2153741 | E11: =D11*100 -> 521.53741 | F11: =D11*200 -> 1043.0748 | G11: =E11/CONFIG!B4*100 -> 1.0430748 | H11: =F11/CONFIG!B4*100 -> 2.0861497 | I11: =MAX(0,100-H11*10-C11*8) -> 60.189382 | J11: =IF(H11>=CONFIG!B15,"Đỏ",IF(H11>=CONFIG!B14,"Vàng","Xanh")) -> Xanh
A12: =INPUT_TREASURY!A12 -> 44469 | B12: =INPUT_TREASURY!B12 -> 50000 | C12: =INPUT_TREASURY!C12 -> 2.3945148 | D12: =INPUT_TREASURY!D12 -> 5.2738849 | E12: =D12*100 -> 527.38849 | F12: =D12*200 -> 1054.777 | G12: =E12/CONFIG!B4*100 -> 1.054777 | H12: =F12/CONFIG!B4*100 -> 2.1095539 | I12: =MAX(0,100-H12*10-C12*8) -> 59.748342 | J12: =IF(H12>=CONFIG!B15,"Đỏ",IF(H12>=CONFIG!B14,"Vàng","Xanh")) -> Xanh
A13: =INPUT_TREASURY!A13 -> 44500 | B13: =INPUT_TREASURY!B13 -> 50000 | C13: =INPUT_TREASURY!C13 -> 2.4157937 | D13: =INPUT_TREASURY!D13 -> 5.3266615 | E13: =D13*100 -> 532.66615 | F13: =D13*200 -> 1065.3323 | G13: =E13/CONFIG!B4*100 -> 1.0653323 | H13: =F13/CONFIG!B4*100 -> 2.1306646 | I13: =MAX(0,100-H13*10-C13*8) -> 59.367005 | J13: =IF(H13>=CONFIG!B15,"Đỏ",IF(H13>=CONFIG!B14,"Vàng","Xanh")) -> Xanh
A14: =INPUT_TREASURY!A14 -> 44530 | B14: =INPUT_TREASURY!B14 -> 50000 | C14: =INPUT_TREASURY!C14 -> 2.4321446 | D14: =INPUT_TREASURY!D14 -> 5.3731768 | E14: =D14*100 -> 537.31768 | F14: =D14*200 -> 1074.6354 | G14: =E14/CONFIG!B4*100 -> 1.0746354 | H14: =F14/CONFIG!B4*100 -> 2.1492707 | I14: =MAX(0,100-H14*10-C14*8) -> 59.050136 | J14: =IF(H14>=CONFIG!B15,"Đỏ",IF(H14>=CONFIG!B14,"Vàng","Xanh")) -> Xanh
A15: =INPUT_TREASURY!A15 -> 44561 | B15: =INPUT_TREASURY!B15 -> 50000 | C15: =INPUT_TREASURY!C15 -> 2.4433126 | D15: =INPUT_TREASURY!D15 -> 5.4129659 | E15: =D15*100 -> 541.29659 | F15: =D15*200 -> 1082.5932 | G15: =E15/CONFIG!B4*100 -> 1.0825932 | H15: =F15/CONFIG!B4*100 -> 2.1651864 | I15: =MAX(0,100-H15*10-C15*8) -> 58.801636 | J15: =IF(H15>=CONFIG!B15,"Đỏ",IF(H15>=CONFIG!B14,"Vàng","Xanh")) -> Xanh
A16: =INPUT_TREASURY!A16 -> 44592 | B16: =INPUT_TREASURY!B16 -> 50000 | C16: =INPUT_TREASURY!C16 -> 2.4491232 | D16: =INPUT_TREASURY!D16 -> 5.4456313 | E16: =D16*100 -> 544.56313 | F16: =D16*200 -> 1089.1263 | G16: =E16/CONFIG!B4*100 -> 1.0891263 | H16: =F16/CONFIG!B4*100 -> 2.1782525 | I16: =MAX(0,100-H16*10-C16*8) -> 58.624489 | J16: =IF(H16>=CONFIG!B15,"Đỏ",IF(H16>=CONFIG!B14,"Vàng","Xanh")) -> Xanh
A17: =INPUT_TREASURY!A17 -> 44620 | B17: =INPUT_TREASURY!B17 -> 50000 | C17: =INPUT_TREASURY!C17 -> 2.449486 | D17: =INPUT_TREASURY!D17 -> 5.4708465 | E17: =D17*100 -> 547.08465 | F17: =D17*200 -> 1094.1693 | G17: =E17/CONFIG!B4*100 -> 1.0941693 | H17: =F17/CONFIG!B4*100 -> 2.1883386 | I17: =MAX(0,100-H17*10-C17*8) -> 58.520726 | J17: =IF(H17>=CONFIG!B15,"Đỏ",IF(H17>=CONFIG!B14,"Vàng","Xanh")) -> Xanh
A18: =INPUT_TREASURY!A18 -> 44651 | B18: =INPUT_TREASURY!B18 -> 50000 | C18: =INPUT_TREASURY!C18 -> 2.4443951 | D18: =INPUT_TREASURY!D18 -> 5.4883598 | E18: =D18*100 -> 548.83598 | F18: =D18*200 -> 1097.672 | G18: =E18/CONFIG!B4*100 -> 1.097672 | H18: =F18/CONFIG!B4*100 -> 2.1953439 | I18: =MAX(0,100-H18*10-C18*8) -> 58.4914 | J18: =IF(H18>=CONFIG!B15,"Đỏ",IF(H18>=CONFIG!B14,"Vàng","Xanh")) -> Xanh
A19: =INPUT_TREASURY!A19 -> 44681 | B19: =INPUT_TREASURY!B19 -> 50000 | C19: =INPUT_TREASURY!C19 -> 2.43393 | D19: =INPUT_TREASURY!D19 -> 5.497996 | E19: =D19*100 -> 549.7996 | F19: =D19*200 -> 1099.5992 | G19: =E19/CONFIG!B4*100 -> 1.0995992 | H19: =F19/CONFIG!B4*100 -> 2.1991984 | I19: =MAX(0,100-H19*10-C19*8) -> 58.536576 | J19: =IF(H19>=CONFIG!B15,"Đỏ",IF(H19>=CONFIG!B14,"Vàng","Xanh")) -> Xanh
A20: =INPUT_TREASURY!A20 -> 44712 | B20: =INPUT_TREASURY!B20 -> 50000 | C20: =INPUT_TREASURY!C20 -> 2.4182541 | D20: =INPUT_TREASURY!D20 -> 5.4996589 | E20: =D20*100 -> 549.96589 | F20: =D20*200 -> 1099.9318 | G20: =E20/CONFIG!B4*100 -> 1.0999318 | H20: =F20/CONFIG!B4*100 -> 2.1998636 | I20: =MAX(0,100-H20*10-C20*8) -> 58.655332 | J20: =IF(H20>=CONFIG!B15,"Đỏ",IF(H20>=CONFIG!B14,"Vàng","Xanh")) -> Xanh
A21: =INPUT_TREASURY!A21 -> 44742 | B21: =INPUT_TREASURY!B21 -> 50000 | C21: =INPUT_TREASURY!C21 -> 2.3976119 | D21: =INPUT_TREASURY!D21 -> 5.4933318 | E21: =D21*100 -> 549.33318 | F21: =D21*200 -> 1098.6664 | G21: =E21/CONFIG!B4*100 -> 1.0986664 | H21: =F21/CONFIG!B4*100 -> 2.1973327 | I21: =MAX(0,100-H21*10-C21*8) -> 58.845777 | J21: =IF(H21>=CONFIG!B15,"Đỏ",IF(H21>=CONFIG!B14,"Vàng","Xanh")) -> Xanh
A22: =INPUT_TREASURY!A22 -> 44773 | B22: =INPUT_TREASURY!B22 -> 50000 | C22: =INPUT_TREASURY!C22 -> 2.3723256 | D22: =INPUT_TREASURY!D22 -> 5.4790781 | E22: =D22*100 -> 547.90781 | F22: =D22*200 -> 1095.8156 | G22: =E22/CONFIG!B4*100 -> 1.0958156 | H22: =F22/CONFIG!B4*100 -> 2.1916312 | I22: =MAX(0,100-H22*10-C22*8) -> 59.105083 | J22: =IF(H22>=CONFIG!B15,"Đỏ",IF(H22>=CONFIG!B14,"Vàng","Xanh")) -> Xanh
A23: =INPUT_TREASURY!A23 -> 44804 | B23: =INPUT_TREASURY!B23 -> 50000 | C23: =INPUT_TREASURY!C23 -> 2.3427898 | D23: =INPUT_TREASURY!D23 -> 5.4570401 | E23: =D23*100 -> 545.70401 | F23: =D23*200 -> 1091.408 | G23: =E23/CONFIG!B4*100 -> 1.091408 | H23: =F23/CONFIG!B4*100 -> 2.182816 | I23: =MAX(0,100-H23*10-C23*8) -> 59.429522 | J23: =IF(H23>=CONFIG!B15,"Đỏ",IF(H23>=CONFIG!B14,"Vàng","Xanh")) -> Xanh
A24: =INPUT_TREASURY!A24 -> 44834 | B24: =INPUT_TREASURY!B24 -> 50000 | C24: =INPUT_TREASURY!C24 -> 2.3094653 | D24: =INPUT_TREASURY!D24 -> 5.4274379 | E24: =D24*100 -> 542.74379 | F24: =D24*200 -> 1085.4876 | G24: =E24/CONFIG!B4*100 -> 1.0854876 | H24: =F24/CONFIG!B4*100 -> 2.1709752 | I24: =MAX(0,100-H24*10-C24*8) -> 59.814526 | J24: =IF(H24>=CONFIG!B15,"Đỏ",IF(H24>=CONFIG!B14,"Vàng","Xanh")) -> Xanh
A25: =INPUT_TREASURY!A25 -> 44865 | B25: =INPUT_TREASURY!B25 -> 50000 | C25: =INPUT_TREASURY!C25 -> 2.2728721 | D25: =INPUT_TREASURY!D25 -> 5.3905675 | E25: =D25*100 -> 539.05675 | F25: =D25*200 -> 1078.1135 | G25: =E25/CONFIG!B4*100 -> 1.0781135 | H25: =F25/CONFIG!B4*100 -> 2.156227 | I25: =MAX(0,100-H25*10-C25*8) -> 60.254753 | J25: =IF(H25>=CONFIG!B15,"Đỏ",IF(H25>=CONFIG!B14,"Vàng","Xanh")) -> Xanh
A26: =INPUT_TREASURY!A26 -> 44895 | B26: =INPUT_TREASURY!B26 -> 50000 | C26: =INPUT_TREASURY!C26 -> 2.2335813 | D26: =INPUT_TREASURY!D26 -> 5.3467971 | E26: =D26*100 -> 534.67971 | F26: =D26*200 -> 1069.3594 | G26: =E26/CONFIG!B4*100 -> 1.0693594 | H26: =F26/CONFIG!B4*100 -> 2.1387188 | I26: =MAX(0,100-H26*10-C26*8) -> 60.744161 | J26: =IF(H26>=CONFIG!B15,"Đỏ",IF(H26>=CONFIG!B14,"Vàng","Xanh")) -> Xanh
A27: =INPUT_TREASURY!A27 -> 44926 | B27: =INPUT_TREASURY!B27 -> 50000 | C27: =INPUT_TREASURY!C27 -> 2.1922061 | D27: =INPUT_TREASURY!D27 -> 5.2965642 | E27: =D27*100 -> 529.65642 | F27: =D27*200 -> 1059.3128 | G27: =E27/CONFIG!B4*100 -> 1.0593128 | H27: =F27/CONFIG!B4*100 -> 2.1186257 | I27: =MAX(0,100-H27*10-C27*8) -> 61.276095 | J27: =IF(H27>=CONFIG!B15,"Đỏ",IF(H27>=CONFIG!B14,"Vàng","Xanh")) -> Xanh
A28: =INPUT_TREASURY!A28 -> 44957 | B28: =INPUT_TREASURY!B28 -> 50000 | C28: =INPUT_TREASURY!C28 -> 2.149392 | D28: =INPUT_TREASURY!D28 -> 5.2403705 | E28: =D28*100 -> 524.03705 | F28: =D28*200 -> 1048.0741 | G28: =E28/CONFIG!B4*100 -> 1.0480741 | H28: =F28/CONFIG!B4*100 -> 2.0961482 | I28: =MAX(0,100-H28*10-C28*8) -> 61.843382 | J28: =IF(H28>=CONFIG!B15,"Đỏ",IF(H28>=CONFIG!B14,"Vàng","Xanh")) -> Xanh
A29: =INPUT_TREASURY!A29 -> 44985 | B29: =INPUT_TREASURY!B29 -> 50000 | C29: =INPUT_TREASURY!C29 -> 2.1058072 | D29: =INPUT_TREASURY!D29 -> 5.1787777 | E29: =D29*100 -> 517.87777 | F29: =D29*200 -> 1035.7555 | G29: =E29/CONFIG!B4*100 -> 1.0357555 | H29: =F29/CONFIG!B4*100 -> 2.0715111 | I29: =MAX(0,100-H29*10-C29*8) -> 62.438432 | J29: =IF(H29>=CONFIG!B15,"Đỏ",IF(H29>=CONFIG!B14,"Vàng","Xanh")) -> Xanh
A30: =INPUT_TREASURY!A30 -> 45016 | B30: =INPUT_TREASURY!B30 -> 50000 | C30: =INPUT_TREASURY!C30 -> 2.0621317 | D30: =INPUT_TREASURY!D30 -> 5.1124011 | E30: =D30*100 -> 511.24011 | F30: =D30*200 -> 1022.4802 | G30: =E30/CONFIG!B4*100 -> 1.0224802 | H30: =F30/CONFIG!B4*100 -> 2.0449604 | I30: =MAX(0,100-H30*10-C30*8) -> 63.053342 | J30: =IF(H30>=CONFIG!B15,"Đỏ",IF(H30>=CONFIG!B14,"Vàng","Xanh")) -> Xanh
A31: =INPUT_TREASURY!A31 -> 45046 | B31: =INPUT_TREASURY!B31 -> 50000 | C31: =INPUT_TREASURY!C31 -> 2.0190472 | D31: =INPUT_TREASURY!D31 -> 5.0419039 | E31: =D31*100 -> 504.19039 | F31: =D31*200 -> 1008.3808 | G31: =E31/CONFIG!B4*100 -> 1.0083808 | H31: =F31/CONFIG!B4*100 -> 2.0167616 | I31: =MAX(0,100-H31*10-C31*8) -> 63.680007 | J31: =IF(H31>=CONFIG!B15,"Đỏ",IF(H31>=CONFIG!B14,"Vàng","Xanh")) -> Xanh
A32: =INPUT_TREASURY!A32 -> 45077 | B32: =INPUT_TREASURY!B32 -> 50000 | C32: =INPUT_TREASURY!C32 -> 1.9772259 | D32: =INPUT_TREASURY!D32 -> 4.9679905 | E32: =D32*100 -> 496.79905 | F32: =D32*200 -> 993.5981 | G32: =E32/CONFIG!B4*100 -> 0.9935981 | H32: =F32/CONFIG!B4*100 -> 1.9871962 | I32: =MAX(0,100-H32*10-C32*8) -> 64.310231 | J32: =IF(H32>=CONFIG!B15,"Đỏ",IF(H32>=CONFIG!B14,"Vàng","Xanh")) -> Xanh
A33: =INPUT_TREASURY!A33 -> 45107 | B33: =INPUT_TREASURY!B33 -> 50000 | C33: =INPUT_TREASURY!C33 -> 1.9373204 | D33: =INPUT_TREASURY!D33 -> 4.8913995 | E33: =D33*100 -> 489.13995 | F33: =D33*200 -> 978.27989 | G33: =E33/CONFIG!B4*100 -> 0.97827989 | H33: =F33/CONFIG!B4*100 -> 1.9565598 | I33: =MAX(0,100-H33*10-C33*8) -> 64.935839 | J33: =IF(H33>=CONFIG!B15,"Đỏ",IF(H33>=CONFIG!B14,"Vàng","Xanh")) -> Xanh
A34: =INPUT_TREASURY!A34 -> 45138 | B34: =INPUT_TREASURY!B34 -> 50000 | C34: =INPUT_TREASURY!C34 -> 1.8999535 | D34: =INPUT_TREASURY!D34 -> 4.812896 | E34: =D34*100 -> 481.2896 | F34: =D34*200 -> 962.5792 | G34: =E34/CONFIG!B4*100 -> 0.9625792 | H34: =F34/CONFIG!B4*100 -> 1.9251584 | I34: =MAX(0,100-H34*10-C34*8) -> 65.548788 | J34: =IF(H34>=CONFIG!B15,"Đỏ",IF(H34>=CONFIG!B14,"Vàng","Xanh")) -> Xanh
A35: =INPUT_TREASURY!A35 -> 45169 | B35: =INPUT_TREASURY!B35 -> 50000 | C35: =INPUT_TREASURY!C35 -> 1.8657083 | D35: =INPUT_TREASURY!D35 -> 4.7332645 | E35: =D35*100 -> 473.32645 | F35: =D35*200 -> 946.65291 | G35: =E35/CONFIG!B4*100 -> 0.94665291 | H35: =F35/CONFIG!B4*100 -> 1.8933058 | I35: =MAX(0,100-H35*10-C35*8) -> 66.141275 | J35: =IF(H35>=CONFIG!B15,"Đỏ",IF(H35>=CONFIG!B14,"Vàng","Xanh")) -> Xanh
A36: =INPUT_TREASURY!A36 -> 45199 | B36: =INPUT_TREASURY!B36 -> 50000 | C36: =INPUT_TREASURY!C36 -> 1.8351191 | D36: =INPUT_TREASURY!D36 -> 4.6533007 | E36: =D36*100 -> 465.33007 | F36: =D36*200 -> 930.66014 | G36: =E36/CONFIG!B4*100 -> 0.93066014 | H36: =F36/CONFIG!B4*100 -> 1.8613203 | I36: =MAX(0,100-H36*10-C36*8) -> 66.705844 | J36: =IF(H36>=CONFIG!B15,"Đỏ",IF(H36>=CONFIG!B14,"Vàng","Xanh")) -> Xanh
A37: =INPUT_TREASURY!A37 -> 45230 | B37: =INPUT_TREASURY!B37 -> 50000 | C37: =INPUT_TREASURY!C37 -> 1.8086633 | D37: =INPUT_TREASURY!D37 -> 4.5738034 | E37: =D37*100 -> 457.38034 | F37: =D37*200 -> 914.76069 | G37: =E37/CONFIG!B4*100 -> 0.91476069 | H37: =F37/CONFIG!B4*100 -> 1.8295214 | I37: =MAX(0,100-H37*10-C37*8) -> 67.23548 | J37: =IF(H37>=CONFIG!B15,"Đỏ",IF(H37>=CONFIG!B14,"Vàng","Xanh")) -> Xanh
A38: =INPUT_TREASURY!A38 -> 45260 | B38: =INPUT_TREASURY!B38 -> 50000 | C38: =INPUT_TREASURY!C38 -> 1.7867537 | D38: =INPUT_TREASURY!D38 -> 4.4955671 | E38: =D38*100 -> 449.55671 | F38: =D38*200 -> 899.11342 | G38: =E38/CONFIG!B4*100 -> 0.89911342 | H38: =F38/CONFIG!B4*100 -> 1.7982268 | I38: =MAX(0,100-H38*10-C38*8) -> 67.723702 | J38: =IF(H38>=CONFIG!B15,"Đỏ",IF(H38>=CONFIG!B14,"Vàng","Xanh")) -> Xanh
A39: =INPUT_TREASURY!A39 -> 45291 | B39: =INPUT_TREASURY!B39 -> 50000 | C39: =INPUT_TREASURY!C39 -> 1.7697322 | D39: =INPUT_TREASURY!D39 -> 4.4193734 | E39: =D39*100 -> 441.93734 | F39: =D39*200 -> 883.87468 | G39: =E39/CONFIG!B4*100 -> 0.88387468 | H39: =F39/CONFIG!B4*100 -> 1.7677494 | I39: =MAX(0,100-H39*10-C39*8) -> 68.164648 | J39: =IF(H39>=CONFIG!B15,"Đỏ",IF(H39>=CONFIG!B14,"Vàng","Xanh")) -> Xanh
A40: =INPUT_TREASURY!A40 -> 45322 | B40: =INPUT_TREASURY!B40 -> 50000 | C40: =INPUT_TREASURY!C40 -> 1.7578645 | D40: =INPUT_TREASURY!D40 -> 4.3459836 | E40: =D40*100 -> 434.59836 | F40: =D40*200 -> 869.19673 | G40: =E40/CONFIG!B4*100 -> 0.86919673 | H40: =F40/CONFIG!B4*100 -> 1.7383935 | I40: =MAX(0,100-H40*10-C40*8) -> 68.55315 | J40: =IF(H40>=CONFIG!B15,"Đỏ",IF(H40>=CONFIG!B14,"Vàng","Xanh")) -> Xanh
A41: =INPUT_TREASURY!A41 -> 45351 | B41: =INPUT_TREASURY!B41 -> 50000 | C41: =INPUT_TREASURY!C41 -> 1.7513356 | D41: =INPUT_TREASURY!D41 -> 4.2761311 | E41: =D41*100 -> 427.61311 | F41: =D41*200 -> 855.22622 | G41: =E41/CONFIG!B4*100 -> 0.85522622 | H41: =F41/CONFIG!B4*100 -> 1.7104524 | I41: =MAX(0,100-H41*10-C41*8) -> 68.884791 | J41: =IF(H41>=CONFIG!B15,"Đỏ",IF(H41>=CONFIG!B14,"Vàng","Xanh")) -> Xanh
A42: =INPUT_TREASURY!A42 -> 45382 | B42: =INPUT_TREASURY!B42 -> 50000 | C42: =INPUT_TREASURY!C42 -> 1.7502475 | D42: =INPUT_TREASURY!D42 -> 4.2105137 | E42: =D42*100 -> 421.05137 | F42: =D42*200 -> 842.10274 | G42: =E42/CONFIG!B4*100 -> 0.84210274 | H42: =F42/CONFIG!B4*100 -> 1.6842055 | I42: =MAX(0,100-H42*10-C42*8) -> 69.155965 | J42: =IF(H42>=CONFIG!B15,"Đỏ",IF(H42>=CONFIG!B14,"Vàng","Xanh")) -> Xanh
A43: =INPUT_TREASURY!A43 -> 45412 | B43: =INPUT_TREASURY!B43 -> 50000 | C43: =INPUT_TREASURY!C43 -> 1.7546172 | D43: =INPUT_TREASURY!D43 -> 4.1497871 | E43: =D43*100 -> 414.97871 | F43: =D43*200 -> 829.95741 | G43: =E43/CONFIG!B4*100 -> 0.82995741 | H43: =F43/CONFIG!B4*100 -> 1.6599148 | I43: =MAX(0,100-H43*10-C43*8) -> 69.363914 | J43: =IF(H43>=CONFIG!B15,"Đỏ",IF(H43>=CONFIG!B14,"Vàng","Xanh")) -> Xanh
A44: =INPUT_TREASURY!A44 -> 45443 | B44: =INPUT_TREASURY!B44 -> 50000 | C44: =INPUT_TREASURY!C44 -> 1.7643765 | D44: =INPUT_TREASURY!D44 -> 4.094558 | E44: =D44*100 -> 409.4558 | F44: =D44*200 -> 818.9116 | G44: =E44/CONFIG!B4*100 -> 0.8189116 | H44: =F44/CONFIG!B4*100 -> 1.6378232 | I44: =MAX(0,100-H44*10-C44*8) -> 69.506756 | J44: =IF(H44>=CONFIG!B15,"Đỏ",IF(H44>=CONFIG!B14,"Vàng","Xanh")) -> Xanh
A45: =INPUT_TREASURY!A45 -> 45473 | B45: =INPUT_TREASURY!B45 -> 50000 | C45: =INPUT_TREASURY!C45 -> 1.7793731 | D45: =INPUT_TREASURY!D45 -> 4.0453783 | E45: =D45*100 -> 404.53783 | F45: =D45*200 -> 809.07566 | G45: =E45/CONFIG!B4*100 -> 0.80907566 | H45: =F45/CONFIG!B4*100 -> 1.6181513 | I45: =MAX(0,100-H45*10-C45*8) -> 69.583502 | J45: =IF(H45>=CONFIG!B15,"Đỏ",IF(H45>=CONFIG!B14,"Vàng","Xanh")) -> Xanh
A46: =INPUT_TREASURY!A46 -> 45504 | B46: =INPUT_TREASURY!B46 -> 50000 | C46: =INPUT_TREASURY!C46 -> 1.7993729 | D46: =INPUT_TREASURY!D46 -> 4.0027394 | E46: =D46*100 -> 400.27394 | F46: =D46*200 -> 800.54788 | G46: =E46/CONFIG!B4*100 -> 0.80054788 | H46: =F46/CONFIG!B4*100 -> 1.6010958 | I46: =MAX(0,100-H46*10-C46*8) -> 69.594059 | J46: =IF(H46>=CONFIG!B15,"Đỏ",IF(H46>=CONFIG!B14,"Vàng","Xanh")) -> Xanh
A47: =INPUT_TREASURY!A47 -> 45535 | B47: =INPUT_TREASURY!B47 -> 50000 | C47: =INPUT_TREASURY!C47 -> 1.824064 | D47: =INPUT_TREASURY!D47 -> 3.9670673 | E47: =D47*100 -> 396.70673 | F47: =D47*200 -> 793.41345 | G47: =E47/CONFIG!B4*100 -> 0.79341345 | H47: =F47/CONFIG!B4*100 -> 1.5868269 | I47: =MAX(0,100-H47*10-C47*8) -> 69.539219 | J47: =IF(H47>=CONFIG!B15,"Đỏ",IF(H47>=CONFIG!B14,"Vàng","Xanh")) -> Xanh
A48: =INPUT_TREASURY!A48 -> 45565 | B48: =INPUT_TREASURY!B48 -> 50000 | C48: =INPUT_TREASURY!C48 -> 1.8530609 | D48: =INPUT_TREASURY!D48 -> 3.9387183 | E48: =D48*100 -> 393.87183 | F48: =D48*200 -> 787.74367 | G48: =E48/CONFIG!B4*100 -> 0.78774367 | H48: =F48/CONFIG!B4*100 -> 1.5754873 | I48: =MAX(0,100-H48*10-C48*8) -> 69.42064 | J48: =IF(H48>=CONFIG!B15,"Đỏ",IF(H48>=CONFIG!B14,"Vàng","Xanh")) -> Xanh
A49: =INPUT_TREASURY!A49 -> 45596 | B49: =INPUT_TREASURY!B49 -> 50000 | C49: =INPUT_TREASURY!C49 -> 1.8859112 | D49: =INPUT_TREASURY!D49 -> 3.9179759 | E49: =D49*100 -> 391.79759 | F49: =D49*200 -> 783.59518 | G49: =E49/CONFIG!B4*100 -> 0.78359518 | H49: =F49/CONFIG!B4*100 -> 1.5671904 | I49: =MAX(0,100-H49*10-C49*8) -> 69.240807 | J49: =IF(H49>=CONFIG!B15,"Đỏ",IF(H49>=CONFIG!B14,"Vàng","Xanh")) -> Xanh
A50: =INPUT_TREASURY!A50 -> 45626 | B50: =INPUT_TREASURY!B50 -> 50000 | C50: =INPUT_TREASURY!C50 -> 1.9221023 | D50: =INPUT_TREASURY!D50 -> 3.9050472 | E50: =D50*100 -> 390.50472 | F50: =D50*200 -> 781.00944 | G50: =E50/CONFIG!B4*100 -> 0.78100944 | H50: =F50/CONFIG!B4*100 -> 1.5620189 | I50: =MAX(0,100-H50*10-C50*8) -> 69.002993 | J50: =IF(H50>=CONFIG!B15,"Đỏ",IF(H50>=CONFIG!B14,"Vàng","Xanh")) -> Xanh
A51: =INPUT_TREASURY!A51 -> 45657 | B51: =INPUT_TREASURY!B51 -> 50000 | C51: =INPUT_TREASURY!C51 -> 1.9610695 | D51: =INPUT_TREASURY!D51 -> 3.9000614 | E51: =D51*100 -> 390.00614 | F51: =D51*200 -> 780.01228 | G51: =E51/CONFIG!B4*100 -> 0.78001228 | H51: =F51/CONFIG!B4*100 -> 1.5600246 | I51: =MAX(0,100-H51*10-C51*8) -> 68.711199 | J51: =IF(H51>=CONFIG!B15,"Đỏ",IF(H51>=CONFIG!B14,"Vàng","Xanh")) -> Xanh
A52: =INPUT_TREASURY!A52 -> 45688 | B52: =INPUT_TREASURY!B52 -> 50000 | C52: =INPUT_TREASURY!C52 -> 2.0022046 | D52: =INPUT_TREASURY!D52 -> 3.9030683 | E52: =D52*100 -> 390.30683 | F52: =D52*200 -> 780.61366 | G52: =E52/CONFIG!B4*100 -> 0.78061366 | H52: =F52/CONFIG!B4*100 -> 1.5612273 | I52: =MAX(0,100-H52*10-C52*8) -> 68.37009 | J52: =IF(H52>=CONFIG!B15,"Đỏ",IF(H52>=CONFIG!B14,"Vàng","Xanh")) -> Xanh
A53: =INPUT_TREASURY!A53 -> 45716 | B53: =INPUT_TREASURY!B53 -> 50000 | C53: =INPUT_TREASURY!C53 -> 2.0448657 | D53: =INPUT_TREASURY!D53 -> 3.9140379 | E53: =D53*100 -> 391.40379 | F53: =D53*200 -> 782.80758 | G53: =E53/CONFIG!B4*100 -> 0.78280758 | H53: =F53/CONFIG!B4*100 -> 1.5656152 | I53: =MAX(0,100-H53*10-C53*8) -> 67.984922 | J53: =IF(H53>=CONFIG!B15,"Đỏ",IF(H53>=CONFIG!B14,"Vàng","Xanh")) -> Xanh
A54: =INPUT_TREASURY!A54 -> 45747 | B54: =INPUT_TREASURY!B54 -> 50000 | C54: =INPUT_TREASURY!C54 -> 2.0883873 | D54: =INPUT_TREASURY!D54 -> 3.9328606 | E54: =D54*100 -> 393.28606 | F54: =D54*200 -> 786.57212 | G54: =E54/CONFIG!B4*100 -> 0.78657212 | H54: =F54/CONFIG!B4*100 -> 1.5731442 | I54: =MAX(0,100-H54*10-C54*8) -> 67.561459 | J54: =IF(H54>=CONFIG!B15,"Đỏ",IF(H54>=CONFIG!B14,"Vàng","Xanh")) -> Xanh
A55: =INPUT_TREASURY!A55 -> 45777 | B55: =INPUT_TREASURY!B55 -> 50000 | C55: =INPUT_TREASURY!C55 -> 2.13209 | D55: =INPUT_TREASURY!D55 -> 3.9593483 | E55: =D55*100 -> 395.93483 | F55: =D55*200 -> 791.86965 | G55: =E55/CONFIG!B4*100 -> 0.79186965 | H55: =F55/CONFIG!B4*100 -> 1.5837393 | I55: =MAX(0,100-H55*10-C55*8) -> 67.105887 | J55: =IF(H55>=CONFIG!B15,"Đỏ",IF(H55>=CONFIG!B14,"Vàng","Xanh")) -> Xanh
A56: =INPUT_TREASURY!A56 -> 45808 | B56: =INPUT_TREASURY!B56 -> 50000 | C56: =INPUT_TREASURY!C56 -> 2.175292 | D56: =INPUT_TREASURY!D56 -> 3.9932363 | E56: =D56*100 -> 399.32363 | F56: =D56*200 -> 798.64726 | G56: =E56/CONFIG!B4*100 -> 0.79864726 | H56: =F56/CONFIG!B4*100 -> 1.5972945 | I56: =MAX(0,100-H56*10-C56*8) -> 66.624719 | J56: =IF(H56>=CONFIG!B15,"Đỏ",IF(H56>=CONFIG!B14,"Vàng","Xanh")) -> Xanh
A57: =INPUT_TREASURY!A57 -> 45838 | B57: =INPUT_TREASURY!B57 -> 50000 | C57: =INPUT_TREASURY!C57 -> 2.2173191 | D57: =INPUT_TREASURY!D57 -> 4.034186 | E57: =D57*100 -> 403.4186 | F57: =D57*200 -> 806.83721 | G57: =E57/CONFIG!B4*100 -> 0.80683721 | H57: =F57/CONFIG!B4*100 -> 1.6136744 | I57: =MAX(0,100-H57*10-C57*8) -> 66.124703 | J57: =IF(H57>=CONFIG!B15,"Đỏ",IF(H57>=CONFIG!B14,"Vàng","Xanh")) -> Xanh
A58: =INPUT_TREASURY!A58 -> 45869 | B58: =INPUT_TREASURY!B58 -> 50000 | C58: =INPUT_TREASURY!C58 -> 2.2575154 | D58: =INPUT_TREASURY!D58 -> 4.0817884 | E58: =D58*100 -> 408.17884 | F58: =D58*200 -> 816.35768 | G58: =E58/CONFIG!B4*100 -> 0.81635768 | H58: =F58/CONFIG!B4*100 -> 1.6327154 | I58: =MAX(0,100-H58*10-C58*8) -> 65.612723 | J58: =IF(H58>=CONFIG!B15,"Đỏ",IF(H58>=CONFIG!B14,"Vàng","Xanh")) -> Xanh
A59: =INPUT_TREASURY!A59 -> 45900 | B59: =INPUT_TREASURY!B59 -> 50000 | C59: =INPUT_TREASURY!C59 -> 2.2952538 | D59: =INPUT_TREASURY!D59 -> 4.1355677 | E59: =D59*100 -> 413.55677 | F59: =D59*200 -> 827.11355 | G59: =E59/CONFIG!B4*100 -> 0.82711355 | H59: =F59/CONFIG!B4*100 -> 1.6542271 | I59: =MAX(0,100-H59*10-C59*8) -> 65.095699 | J59: =IF(H59>=CONFIG!B15,"Đỏ",IF(H59>=CONFIG!B14,"Vàng","Xanh")) -> Xanh
A60: =INPUT_TREASURY!A60 -> 45930 | B60: =INPUT_TREASURY!B60 -> 50000 | C60: =INPUT_TREASURY!C60 -> 2.3299453 | D60: =INPUT_TREASURY!D60 -> 4.1949867 | E60: =D60*100 -> 419.49867 | F60: =D60*200 -> 838.99734 | G60: =E60/CONFIG!B4*100 -> 0.83899734 | H60: =F60/CONFIG!B4*100 -> 1.6779947 | I60: =MAX(0,100-H60*10-C60*8) -> 64.580491 | J60: =IF(H60>=CONFIG!B15,"Đỏ",IF(H60>=CONFIG!B14,"Vàng","Xanh")) -> Xanh
A61: =INPUT_TREASURY!A61 -> 45961 | B61: =INPUT_TREASURY!B61 -> 50000 | C61: =INPUT_TREASURY!C61 -> 2.3610486 | D61: =INPUT_TREASURY!D61 -> 4.2594516 | E61: =D61*100 -> 425.94516 | F61: =D61*200 -> 851.89031 | G61: =E61/CONFIG!B4*100 -> 0.85189031 | H61: =F61/CONFIG!B4*100 -> 1.7037806 | I61: =MAX(0,100-H61*10-C61*8) -> 64.073805 | J61: =IF(H61>=CONFIG!B15,"Đỏ",IF(H61>=CONFIG!B14,"Vàng","Xanh")) -> Xanh
A62: =INPUT_TREASURY!A62 -> 45991 | B62: =INPUT_TREASURY!B62 -> 50000 | C62: =INPUT_TREASURY!C62 -> 2.3880783 | D62: =INPUT_TREASURY!D62 -> 4.3283183 | E62: =D62*100 -> 432.83183 | F62: =D62*200 -> 865.66365 | G62: =E62/CONFIG!B4*100 -> 0.86566365 | H62: =F62/CONFIG!B4*100 -> 1.7313273 | I62: =MAX(0,100-H62*10-C62*8) -> 63.582101 | J62: =IF(H62>=CONFIG!B15,"Đỏ",IF(H62>=CONFIG!B14,"Vàng","Xanh")) -> Xanh
A63: =INPUT_TREASURY!A63 -> 46022 | B63: =INPUT_TREASURY!B63 -> 50000 | C63: =INPUT_TREASURY!C63 -> 2.4106127 | D63: =INPUT_TREASURY!D63 -> 4.4008987 | E63: =D63*100 -> 440.08987 | F63: =D63*200 -> 880.17973 | G63: =E63/CONFIG!B4*100 -> 0.88017973 | H63: =F63/CONFIG!B4*100 -> 1.7603595 | I63: =MAX(0,100-H63*10-C63*8) -> 63.111504 | J63: =IF(H63>=CONFIG!B15,"Đỏ",IF(H63>=CONFIG!B14,"Vàng","Xanh")) -> Xanh
A64: =INPUT_TREASURY!A64 -> 46053 | B64: =INPUT_TREASURY!B64 -> 50000 | C64: =INPUT_TREASURY!C64 -> 2.4283 | D64: =INPUT_TREASURY!D64 -> 4.4764676 | E64: =D64*100 -> 447.64676 | F64: =D64*200 -> 895.29352 | G64: =E64/CONFIG!B4*100 -> 0.89529352 | H64: =F64/CONFIG!B4*100 -> 1.790587 | I64: =MAX(0,100-H64*10-C64*8) -> 62.66773 | J64: =IF(H64>=CONFIG!B15,"Đỏ",IF(H64>=CONFIG!B14,"Vàng","Xanh")) -> Xanh
A65: =INPUT_TREASURY!A65 -> 46081 | B65: =INPUT_TREASURY!B65 -> 50000 | C65: =INPUT_TREASURY!C65 -> 2.4408643 | D65: =INPUT_TREASURY!D65 -> 4.55427 | E65: =D65*100 -> 455.427 | F65: =D65*200 -> 910.854 | G65: =E65/CONFIG!B4*100 -> 0.910854 | H65: =F65/CONFIG!B4*100 -> 1.821708 | I65: =MAX(0,100-H65*10-C65*8) -> 62.256005 | J65: =IF(H65>=CONFIG!B15,"Đỏ",IF(H65>=CONFIG!B14,"Vàng","Xanh")) -> Xanh
A66: =INPUT_TREASURY!A66 -> 46112 | B66: =INPUT_TREASURY!B66 -> 50000 | C66: =INPUT_TREASURY!C66 -> 2.4481096 | D66: =INPUT_TREASURY!D66 -> 4.6335285 | E66: =D66*100 -> 463.35285 | F66: =D66*200 -> 926.7057 | G66: =E66/CONFIG!B4*100 -> 0.9267057 | H66: =F66/CONFIG!B4*100 -> 1.8534114 | I66: =MAX(0,100-H66*10-C66*8) -> 61.88101 | J66: =IF(H66>=CONFIG!B15,"Đỏ",IF(H66>=CONFIG!B14,"Vàng","Xanh")) -> Xanh
A67: =INPUT_TREASURY!A67 -> 46142 | B67: =INPUT_TREASURY!B67 -> 50000 | C67: =INPUT_TREASURY!C67 -> 2.4499227 | D67: =INPUT_TREASURY!D67 -> 4.7134511 | E67: =D67*100 -> 471.34511 | F67: =D67*200 -> 942.69022 | G67: =E67/CONFIG!B4*100 -> 0.94269022 | H67: =F67/CONFIG!B4*100 -> 1.8853804 | I67: =MAX(0,100-H67*10-C67*8) -> 61.546814 | J67: =IF(H67>=CONFIG!B15,"Đỏ",IF(H67>=CONFIG!B14,"Vàng","Xanh")) -> Xanh

Sheet PROC_SIGNAL
A1: PROC_SIGNAL - Early Warning Signals | B1: PROC_SIGNAL - Early Warning Signals | C1: PROC_SIGNAL - Early Warning Signals | D1: PROC_SIGNAL - Early Warning Signals | E1: PROC_SIGNAL - Early Warning Signals | F1: PROC_SIGNAL - Early Warning Signals
A3: date | B3: signal | C3: metric_value | D3: status | E3: level | F3: comment
A4: =PROC_MACRO!A67 -> 46142 | B4: ="VNIBOR spike" -> VNIBOR spike | C4: =PROC_MACRO!D67 -> 2.2684259 | D4: =IF(C4>=CONFIG!B7,"Breach",IF(C4>=CONFIG!B6,"Watch","Normal")) -> Normal | E4: =IF(C4>=CONFIG!B7,"Đỏ",IF(C4>=CONFIG!B6,"Vàng","Xanh")) -> Xanh | F4: ="Lãi suất ON cao gây áp lực chi phí vốn và duration." -> Lãi suất ON cao gây áp lực chi phí vốn và duration.
A5: =PROC_MACRO!A67 -> 46142 | B5: ="FX pressure" -> FX pressure | C5: =ABS(PROC_MACRO!G67) -> 0.021313678 | D5: =IF(C5>=CONFIG!B9,"Breach",IF(C5>=CONFIG!B8,"Watch","Normal")) -> Normal | E5: =IF(C5>=CONFIG!B9,"Đỏ",IF(C5>=CONFIG!B8,"Vàng","Xanh")) -> Xanh | F5: ="Biến động USD/VND theo tháng." -> Biến động USD/VND theo tháng.
A6: =PROC_MACRO!A67 -> 46142 | B6: ="LDR high" -> LDR high | C6: =PROC_ABBANK!F67 -> 95.561516 | D6: =IF(C6>=CONFIG!B11,"Breach",IF(C6>=CONFIG!B10,"Watch","Normal")) -> Breach | E6: =IF(C6>=CONFIG!B11,"Đỏ",IF(C6>=CONFIG!B10,"Vàng","Xanh")) -> Đỏ | F6: ="LDR cao làm giảm dư địa tăng trưởng tín dụng." -> LDR cao làm giảm dư địa tăng trưởng tín dụng.
A7: =PROC_MACRO!A67 -> 46142 | B7: ="NPL risk" -> NPL risk | C7: =PROC_ABBANK!G67 -> 2.3499227 | D7: =IF(C7>=CONFIG!B13,"Breach",IF(C7>=CONFIG!B12,"Watch","Normal")) -> Normal | E7: =IF(C7>=CONFIG!B13,"Đỏ",IF(C7>=CONFIG!B12,"Vàng","Xanh")) -> Xanh | F7: ="NPL tăng làm tăng áp lực trích lập." -> NPL tăng làm tăng áp lực trích lập.
A8: =PROC_MACRO!A67 -> 46142 | B8: ="Treasury stress loss" -> Treasury stress loss | C8: =PROC_TREASURY!H67 -> 1.8853804 | D8: =IF(C8>=CONFIG!B15,"Breach",IF(C8>=CONFIG!B14,"Watch","Normal")) -> Normal | E8: =IF(C8>=CONFIG!B15,"Đỏ",IF(C8>=CONFIG!B14,"Vàng","Xanh")) -> Xanh | F8: ="Loss 200bps so với vốn Treasury." -> Loss 200bps so với vốn Treasury.

Sheet PROC_RECOMMENDATION
A1: PROC_RECOMMENDATION - Action Engine | B1: PROC_RECOMMENDATION - Action Engine | C1: PROC_RECOMMENDATION - Action Engine | D1: PROC_RECOMMENDATION - Action Engine | E1: PROC_RECOMMENDATION - Action Engine
A3: priority | B3: trigger | C3: recommended_action | D3: owner | E3: rationale
A4: 1 | B4: VNIBOR spike | C4: Giữ duration ngắn; hạn chế tăng vị thế bond dài hạn | D4: Treasury | E4: VNIBOR cao thường làm tăng risk premium và gây MTM loss cho duration dài.
A5: 2 | B5: FX pressure | C5: Theo dõi trạng thái USD; cân nhắc hedge/giảm trạng thái mở | D5: Treasury | E5: Biến động tỷ giá có thể ảnh hưởng thanh khoản ngoại tệ và tâm lý huy động.
A6: 3 | B6: LDR high | C6: Kiểm soát tăng trưởng tín dụng; ưu tiên huy động CASA/kỳ hạn bền vững | D6: Finance/ALM | E6: LDR cao làm giảm dư địa thanh khoản và tăng cạnh tranh huy động.
A7: 4 | B7: NPL risk | C7: Rà soát phân khúc rủi ro; tăng cảnh báo sớm tín dụng | D7: Risk/Business | E7: NPL tăng làm tăng provisioning và giảm ROA/ROE.
A8: 5 | B8: Treasury stress loss | C8: Giảm DV01 hoặc đặt stop-loss theo vốn Treasury | D8: Treasury/Risk | E8: Stress loss vượt risk appetite làm suy giảm vốn chịu rủi ro của Treasury.

Sheet DASH_EXECUTIVE
A1: DASH_EXECUTIVE - CEO 3-Minute View | B1: DASH_EXECUTIVE - CEO 3-Minute View | C1: DASH_EXECUTIVE - CEO 3-Minute View | D1: DASH_EXECUTIVE - CEO 3-Minute View | E1: DASH_EXECUTIVE - CEO 3-Minute View | F1: DASH_EXECUTIVE - CEO 3-Minute View | G1: DASH_EXECUTIVE - CEO 3-Minute View | H1: DASH_EXECUTIVE - CEO 3-Minute View | I1: DASH_EXECUTIVE - CEO 3-Minute View | J1: DASH_EXECUTIVE - CEO 3-Minute View
A3: Area | B3: Metric | C3: Latest | D3: Status/Score | E3: Interpretation | G3: Top Alerts & Recommended Actions
A4: Macro | B4: Macro score | C4: =PROC_MACRO!K67 -> 54.404088 | D4: =IF(C4>=70,"Xanh",IF(C4>=50,"Vàng","Đỏ")) -> Vàng | E4: Điểm vĩ mô tổng hợp từ lạm phát, thanh khoản, tỷ giá | G4: Signal | H4: Level | I4: Action | J4: Owner
A5: Macro | B5: CPI | C5: =PROC_MACRO!B67 -> 5.0097812 | D5: =IF(C5>=4.5,"Đỏ",IF(C5>=3.5,"Vàng","Xanh")) -> Đỏ | E5: Áp lực lạm phát | G5: =PROC_SIGNAL!B4 -> VNIBOR spike | H5: =PROC_SIGNAL!E4 -> Xanh | I5: =INDEX(PROC_RECOMMENDATION!C:C,MATCH(PROC_SIGNAL!B4,PROC_RECOMMENDATION!B:B,0)) -> Giữ duration ngắn; hạn chế tăng vị thế bond dài hạn | J5: =INDEX(PROC_RECOMMENDATION!D:D,MATCH(PROC_SIGNAL!B4,PROC_RECOMMENDATION!B:B,0)) -> Treasury
A6: Macro | B6: VNIBOR ON | C6: =PROC_MACRO!D67 -> 2.2684259 | D6: =IF(C6>=CONFIG!B7,"Đỏ",IF(C6>=CONFIG!B6,"Vàng","Xanh")) -> Xanh | E6: Áp lực thanh khoản ngắn hạn | G6: =PROC_SIGNAL!B5 -> FX pressure | H6: =PROC_SIGNAL!E5 -> Xanh | I6: =INDEX(PROC_RECOMMENDATION!C:C,MATCH(PROC_SIGNAL!B5,PROC_RECOMMENDATION!B:B,0)) -> Theo dõi trạng thái USD; cân nhắc hedge/giảm trạng thái mở | J6: =INDEX(PROC_RECOMMENDATION!D:D,MATCH(PROC_SIGNAL!B5,PROC_RECOMMENDATION!B:B,0)) -> Treasury
A7: ABBank | B7: ABBank score | C7: =PROC_ABBANK!K67 -> 67.240929 | D7: =IF(C7>=70,"Xanh",IF(C7>=50,"Vàng","Đỏ")) -> Vàng | E7: Điểm tổng hợp tăng trưởng, funding, chất lượng tài sản | G7: =PROC_SIGNAL!B6 -> LDR high | H7: =PROC_SIGNAL!E6 -> Đỏ | I7: =INDEX(PROC_RECOMMENDATION!C:C,MATCH(PROC_SIGNAL!B6,PROC_RECOMMENDATION!B:B,0)) -> Kiểm soát tăng trưởng tín dụng; ưu tiên huy động CASA/kỳ hạn bền vững | J7: =INDEX(PROC_RECOMMENDATION!D:D,MATCH(PROC_SIGNAL!B6,PROC_RECOMMENDATION!B:B,0)) -> Finance/ALM
A8: ABBank | B8: LDR | C8: =PROC_ABBANK!F67 -> 95.561516 | D8: =IF(C8>=CONFIG!B11,"Đỏ",IF(C8>=CONFIG!B10,"Vàng","Xanh")) -> Đỏ | E8: Sức ép huy động/cho vay | G8: =PROC_SIGNAL!B7 -> NPL risk | H8: =PROC_SIGNAL!E7 -> Xanh | I8: =INDEX(PROC_RECOMMENDATION!C:C,MATCH(PROC_SIGNAL!B7,PROC_RECOMMENDATION!B:B,0)) -> Rà soát phân khúc rủi ro; tăng cảnh báo sớm tín dụng | J8: =INDEX(PROC_RECOMMENDATION!D:D,MATCH(PROC_SIGNAL!B7,PROC_RECOMMENDATION!B:B,0)) -> Risk/Business
A9: ABBank | B9: NPL | C9: =PROC_ABBANK!G67 -> 2.3499227 | D9: =IF(C9>=CONFIG!B13,"Đỏ",IF(C9>=CONFIG!B12,"Vàng","Xanh")) -> Xanh | E9: Chất lượng tài sản | G9: =PROC_SIGNAL!B8 -> Treasury stress loss | H9: =PROC_SIGNAL!E8 -> Xanh | I9: =INDEX(PROC_RECOMMENDATION!C:C,MATCH(PROC_SIGNAL!B8,PROC_RECOMMENDATION!B:B,0)) -> Giảm DV01 hoặc đặt stop-loss theo vốn Treasury | J9: =INDEX(PROC_RECOMMENDATION!D:D,MATCH(PROC_SIGNAL!B8,PROC_RECOMMENDATION!B:B,0)) -> Treasury/Risk
A10: Treasury | B10: DV01 | C10: =PROC_TREASURY!D67 -> 4.7134511 | D10: =IF(C10>=6,"Vàng","Xanh") -> Xanh | E10: P&L sensitivity trên mỗi 1bp
A11: Treasury | B11: Stress loss 200bps / capital | C11: =PROC_TREASURY!H67 -> 1.8853804 | D11: =IF(C11>=CONFIG!B15,"Đỏ",IF(C11>=CONFIG!B14,"Vàng","Xanh")) -> Xanh | E11: Mức lỗ stress so với vốn Treasury

Sheet DASH_MACRO
A1: DASH_MACRO - Macro & Money Market | B1: DASH_MACRO - Macro & Money Market | C1: DASH_MACRO - Macro & Money Market | D1: DASH_MACRO - Macro & Money Market | E1: DASH_MACRO - Macro & Money Market | F1: DASH_MACRO - Macro & Money Market | G1: DASH_MACRO - Macro & Money Market | H1: DASH_MACRO - Macro & Money Market
A3: date | B3: CPI | C3: USD/VND | D3: VNIBOR ON | E3: Credit-deposit gap | F3: Macro score
A4: =PROC_MACRO!A56 -> 45808 | B4: =PROC_MACRO!B56 -> 3.0821703 | C4: =PROC_MACRO!C56 -> 24627.888 | D4: =PROC_MACRO!D56 -> 4.4625717 | E4: =PROC_MACRO!H56 -> -0.27650834 | F4: =PROC_MACRO!K56 -> 78.995139
A5: =PROC_MACRO!A57 -> 45838 | B5: =PROC_MACRO!B57 -> 3.2521778 | C5: =PROC_MACRO!C57 -> 24623.39 | D5: =PROC_MACRO!D57 -> 4.2805852 | E5: =PROC_MACRO!H57 -> -0.31736328 | F5: =PROC_MACRO!K57 -> 78.91782
A6: =PROC_MACRO!A58 -> 45869 | B6: =PROC_MACRO!B58 -> 3.4288183 | C6: =PROC_MACRO!C58 -> 24615.03 | D6: =PROC_MACRO!D58 -> 4.0769659 | E6: =PROC_MACRO!H58 -> -0.3464989 | F6: =PROC_MACRO!K58 -> 78.847208
A7: =PROC_MACRO!A59 -> 45900 | B7: =PROC_MACRO!B59 -> 3.6102832 | C7: =PROC_MACRO!C59 -> 24603.814 | D7: =PROC_MACRO!D59 -> 3.8573568 | E7: =PROC_MACRO!H59 -> -0.36391175 | F7: =PROC_MACRO!K59 -> 66.544956
A8: =PROC_MACRO!A60 -> 45930 | B8: =PROC_MACRO!B60 -> 3.7947045 | C8: =PROC_MACRO!C60 -> 24590.829 | D8: =PROC_MACRO!D60 -> 3.6278441 | E8: =PROC_MACRO!H60 -> -0.36972595 | F8: =PROC_MACRO!K60 -> 66.512517
A9: =PROC_MACRO!A61 -> 45961 | B9: =PROC_MACRO!B61 -> 3.9801778 | C9: =PROC_MACRO!C61 -> 24577.212 | D9: =PROC_MACRO!D61 -> 3.3947884 | E9: =PROC_MACRO!H61 -> -0.36418951 | F9: =PROC_MACRO!K61 -> 66.500814
A10: =PROC_MACRO!A62 -> 45991 | B10: =PROC_MACRO!B62 -> 4.1647856 | C10: =PROC_MACRO!C62 -> 24564.116 | D10: =PROC_MACRO!D62 -> 3.1646485 | E10: =PROC_MACRO!H62 -> -0.34766933 | F10: =PROC_MACRO!K62 -> 66.510209
A11: =PROC_MACRO!A63 -> 46022 | B11: =PROC_MACRO!B63 -> 4.3466211 | C11: =PROC_MACRO!C63 -> 24552.679 | D11: =PROC_MACRO!D63 -> 2.9438024 | E11: =PROC_MACRO!H63 -> -0.32064493 | F11: =PROC_MACRO!K63 -> 66.540484
A12: =PROC_MACRO!A64 -> 46053 | B12: =PROC_MACRO!B64 -> 4.5238117 | C12: =PROC_MACRO!C64 -> 24543.995 | D12: =PROC_MACRO!D64 -> 2.7383704 | E12: =PROC_MACRO!H64 -> -0.28370111 | F12: =PROC_MACRO!K64 -> 54.340835
A13: =PROC_MACRO!A65 -> 46081 | B13: =PROC_MACRO!B65 -> 4.6945422 | C13: =PROC_MACRO!C65 -> 24539.08 | D13: =PROC_MACRO!D65 -> 2.554046 | E13: =PROC_MACRO!H65 -> -0.23751947 | F13: =PROC_MACRO!K65 -> 54.409885
A14: =PROC_MACRO!A66 -> 46112 | B14: =PROC_MACRO!B66 -> 4.8570769 | C14: =PROC_MACRO!C66 -> 24538.846 | D14: =PROC_MACRO!D66 -> 2.3959372 | E14: =PROC_MACRO!H66 -> -0.18286904 | F14: =PROC_MACRO!K66 -> 54.495714
A15: =PROC_MACRO!A67 -> 46142 | B15: =PROC_MACRO!B67 -> 5.0097812 | C15: =PROC_MACRO!C67 -> 24544.076 | D15: =PROC_MACRO!D67 -> 2.2684259 | E15: =PROC_MACRO!H67 -> -0.12059602 | F15: =PROC_MACRO!K67 -> 54.404088

Sheet DASH_ABBANK
A1: DASH_ABBANK - ABBank Core Business | B1: DASH_ABBANK - ABBank Core Business | C1: DASH_ABBANK - ABBank Core Business | D1: DASH_ABBANK - ABBank Core Business | E1: DASH_ABBANK - ABBank Core Business | F1: DASH_ABBANK - ABBank Core Business | G1: DASH_ABBANK - ABBank Core Business | H1: DASH_ABBANK - ABBank Core Business
A3: date | B3: Loan growth | C3: Deposit growth | D3: CASA | E3: NIM | F3: LDR | G3: NPL | H3: ABBank score
A4: =PROC_ABBANK!A56 -> 45808 | B4: =PROC_ABBANK!B56 -> 7.9348391 | C4: =PROC_ABBANK!C56 -> 10.676 | D4: =PROC_ABBANK!D56 -> 12.233091 | E4: =PROC_ABBANK!E56 -> 3.2777174 | F4: =PROC_ABBANK!F56 -> 92.519427 | G4: =PROC_ABBANK!G56 -> 2.075292 | H4: =PROC_ABBANK!K56 -> 69.559527
A5: =PROC_ABBANK!A57 -> 45838 | B5: =PROC_ABBANK!B57 -> 8.1548509 | C5: =PROC_ABBANK!C57 -> 10.747796 | D5: =PROC_ABBANK!D57 -> 12.335465 | E5: =PROC_ABBANK!E57 -> 3.2900867 | F5: =PROC_ABBANK!F57 -> 92.612453 | G5: =PROC_ABBANK!G57 -> 2.1173191 | H5: =PROC_ABBANK!K57 -> 69.434694
A6: =PROC_ABBANK!A58 -> 45869 | B6: =PROC_ABBANK!B58 -> 8.3852859 | C6: =PROC_ABBANK!C58 -> 10.789198 | D6: =PROC_ABBANK!D58 -> 12.454471 | E6: =PROC_ABBANK!E58 -> 3.2975646 | F6: =PROC_ABBANK!F58 -> 92.756122 | G6: =PROC_ABBANK!G58 -> 2.1575154 | H6: =PROC_ABBANK!K58 -> 69.276107
A7: =PROC_ABBANK!A59 -> 45900 | B7: =PROC_ABBANK!B59 -> 8.6233022 | C7: =PROC_ABBANK!C59 -> 10.799558 | D7: =PROC_ABBANK!D59 -> 12.588919 | E7: =PROC_ABBANK!E59 -> 3.2999988 | F7: =PROC_ABBANK!F59 -> 92.949117 | G7: =PROC_ABBANK!G59 -> 2.1952538 | H7: =PROC_ABBANK!K59 -> 69.086076
A8: =PROC_ABBANK!A60 -> 45930 | B8: =PROC_ABBANK!B60 -> 8.8659643 | C8: =PROC_ABBANK!C60 -> 10.778716 | D8: =PROC_ABBANK!D60 -> 12.737467 | E8: =PROC_ABBANK!E60 -> 3.2973396 | F8: =PROC_ABBANK!F60 -> 93.188253 | G8: =PROC_ABBANK!G60 -> 2.2299453 | H8: =PROC_ABBANK!K60 -> 68.868779
A9: =PROC_ABBANK!A61 -> 45961 | B9: =PROC_ABBANK!B61 -> 9.1102794 | C9: =PROC_ABBANK!C61 -> 10.726998 | D9: =PROC_ABBANK!D61 -> 12.898629 | E9: =PROC_ABBANK!E61 -> 3.2896412 | F9: =PROC_ABBANK!F61 -> 93.468551 | G9: =PROC_ABBANK!G61 -> 2.2610486 | H9: =PROC_ABBANK!K61 -> 68.63015
A10: =PROC_ABBANK!A62 -> 45991 | B10: =PROC_ABBANK!B62 -> 9.3532345 | C10: =PROC_ABBANK!C62 -> 10.645208 | D10: =PROC_ABBANK!D62 -> 13.070796 | E10: =PROC_ABBANK!E62 -> 3.2770605 | F10: =PROC_ABBANK!F62 -> 93.783393 | G10: =PROC_ABBANK!G62 -> 2.2880783 | H10: =PROC_ABBANK!K62 -> 68.377688
A11: =PROC_ABBANK!A63 -> 46022 | B11: =PROC_ABBANK!B63 -> 9.5918331 | C11: =PROC_ABBANK!C63 -> 10.534625 | D11: =PROC_ABBANK!D63 -> 13.252247 | E11: =PROC_ABBANK!E63 -> 3.2598538 | F11: =PROC_ABBANK!F63 -> 94.124735 | G11: =PROC_ABBANK!G63 -> 2.3106127 | H11: =PROC_ABBANK!K63 -> 68.120191
A12: =PROC_ABBANK!A64 -> 46053 | B12: =PROC_ABBANK!B64 -> 9.8231327 | C12: =PROC_ABBANK!C64 -> 10.396974 | D12: =PROC_ABBANK!D64 -> 13.441169 | E12: =PROC_ABBANK!E64 -> 3.2383717 | F12: =PROC_ABBANK!F64 -> 94.483392 | G12: =PROC_ABBANK!G64 -> 2.3283 | H12: =PROC_ABBANK!K64 -> 67.867416
A13: =PROC_ABBANK!A65 -> 46081 | B13: =PROC_ABBANK!B65 -> 10.044281 | C13: =PROC_ABBANK!C65 -> 10.234403 | D13: =PROC_ABBANK!D65 -> 13.635675 | E13: =PROC_ABBANK!E65 -> 3.2130517 | F13: =PROC_ABBANK!F65 -> 94.849369 | G13: =PROC_ABBANK!G65 -> 2.3408643 | H13: =PROC_ABBANK!K65 -> 67.629694
A14: =PROC_ABBANK!A66 -> 46112 | B14: =PROC_ABBANK!B66 -> 10.252549 | C14: =PROC_ABBANK!C66 -> 10.049448 | D14: =PROC_ABBANK!D66 -> 13.833821 | E14: =PROC_ABBANK!E66 -> 3.1844099 | F14: =PROC_ABBANK!F66 -> 95.212233 | G14: =PROC_ABBANK!G66 -> 2.3481096 | H14: =PROC_ABBANK!K66 -> 67.417485
A15: =PROC_ABBANK!A67 -> 46142 | B15: =PROC_ABBANK!B67 -> 10.445371 | C15: =PROC_ABBANK!C67 -> 9.8449958 | D15: =PROC_ABBANK!D67 -> 14.033628 | E15: =PROC_ABBANK!E67 -> 3.1530296 | F15: =PROC_ABBANK!F67 -> 95.561516 | G15: =PROC_ABBANK!G67 -> 2.3499227 | H15: =PROC_ABBANK!K67 -> 67.240929

Sheet DASH_TREASURY
A1: DASH_TREASURY - Portfolio Risk | B1: DASH_TREASURY - Portfolio Risk | C1: DASH_TREASURY - Portfolio Risk | D1: DASH_TREASURY - Portfolio Risk | E1: DASH_TREASURY - Portfolio Risk | F1: DASH_TREASURY - Portfolio Risk | G1: DASH_TREASURY - Portfolio Risk | H1: DASH_TREASURY - Portfolio Risk
A3: date | B3: Portfolio size | C3: Duration | D3: DV01 | E3: Stress loss 100bps | F3: Stress loss 200bps | G3: Loss 200bps / capital | H3: Risk level
A4: =PROC_TREASURY!A56 -> 45808 | B4: =PROC_TREASURY!B56 -> 50000 | C4: =PROC_TREASURY!C56 -> 2.175292 | D4: =PROC_TREASURY!D56 -> 3.9932363 | E4: =PROC_TREASURY!E56 -> 399.32363 | F4: =PROC_TREASURY!F56 -> 798.64726 | G4: =PROC_TREASURY!H56 -> 1.5972945 | H4: =PROC_TREASURY!J56 -> Xanh
A5: =PROC_TREASURY!A57 -> 45838 | B5: =PROC_TREASURY!B57 -> 50000 | C5: =PROC_TREASURY!C57 -> 2.2173191 | D5: =PROC_TREASURY!D57 -> 4.034186 | E5: =PROC_TREASURY!E57 -> 403.4186 | F5: =PROC_TREASURY!F57 -> 806.83721 | G5: =PROC_TREASURY!H57 -> 1.6136744 | H5: =PROC_TREASURY!J57 -> Xanh
A6: =PROC_TREASURY!A58 -> 45869 | B6: =PROC_TREASURY!B58 -> 50000 | C6: =PROC_TREASURY!C58 -> 2.2575154 | D6: =PROC_TREASURY!D58 -> 4.0817884 | E6: =PROC_TREASURY!E58 -> 408.17884 | F6: =PROC_TREASURY!F58 -> 816.35768 | G6: =PROC_TREASURY!H58 -> 1.6327154 | H6: =PROC_TREASURY!J58 -> Xanh
A7: =PROC_TREASURY!A59 -> 45900 | B7: =PROC_TREASURY!B59 -> 50000 | C7: =PROC_TREASURY!C59 -> 2.2952538 | D7: =PROC_TREASURY!D59 -> 4.1355677 | E7: =PROC_TREASURY!E59 -> 413.55677 | F7: =PROC_TREASURY!F59 -> 827.11355 | G7: =PROC_TREASURY!H59 -> 1.6542271 | H7: =PROC_TREASURY!J59 -> Xanh
A8: =PROC_TREASURY!A60 -> 45930 | B8: =PROC_TREASURY!B60 -> 50000 | C8: =PROC_TREASURY!C60 -> 2.3299453 | D8: =PROC_TREASURY!D60 -> 4.1949867 | E8: =PROC_TREASURY!E60 -> 419.49867 | F8: =PROC_TREASURY!F60 -> 838.99734 | G8: =PROC_TREASURY!H60 -> 1.6779947 | H8: =PROC_TREASURY!J60 -> Xanh
A9: =PROC_TREASURY!A61 -> 45961 | B9: =PROC_TREASURY!B61 -> 50000 | C9: =PROC_TREASURY!C61 -> 2.3610486 | D9: =PROC_TREASURY!D61 -> 4.2594516 | E9: =PROC_TREASURY!E61 -> 425.94516 | F9: =PROC_TREASURY!F61 -> 851.89031 | G9: =PROC_TREASURY!H61 -> 1.7037806 | H9: =PROC_TREASURY!J61 -> Xanh
A10: =PROC_TREASURY!A62 -> 45991 | B10: =PROC_TREASURY!B62 -> 50000 | C10: =PROC_TREASURY!C62 -> 2.3880783 | D10: =PROC_TREASURY!D62 -> 4.3283183 | E10: =PROC_TREASURY!E62 -> 432.83183 | F10: =PROC_TREASURY!F62 -> 865.66365 | G10: =PROC_TREASURY!H62 -> 1.7313273 | H10: =PROC_TREASURY!J62 -> Xanh
A11: =PROC_TREASURY!A63 -> 46022 | B11: =PROC_TREASURY!B63 -> 50000 | C11: =PROC_TREASURY!C63 -> 2.4106127 | D11: =PROC_TREASURY!D63 -> 4.4008987 | E11: =PROC_TREASURY!E63 -> 440.08987 | F11: =PROC_TREASURY!F63 -> 880.17973 | G11: =PROC_TREASURY!H63 -> 1.7603595 | H11: =PROC_TREASURY!J63 -> Xanh
A12: =PROC_TREASURY!A64 -> 46053 | B12: =PROC_TREASURY!B64 -> 50000 | C12: =PROC_TREASURY!C64 -> 2.4283 | D12: =PROC_TREASURY!D64 -> 4.4764676 | E12: =PROC_TREASURY!E64 -> 447.64676 | F12: =PROC_TREASURY!F64 -> 895.29352 | G12: =PROC_TREASURY!H64 -> 1.790587 | H12: =PROC_TREASURY!J64 -> Xanh
A13: =PROC_TREASURY!A65 -> 46081 | B13: =PROC_TREASURY!B65 -> 50000 | C13: =PROC_TREASURY!C65 -> 2.4408643 | D13: =PROC_TREASURY!D65 -> 4.55427 | E13: =PROC_TREASURY!E65 -> 455.427 | F13: =PROC_TREASURY!F65 -> 910.854 | G13: =PROC_TREASURY!H65 -> 1.821708 | H13: =PROC_TREASURY!J65 -> Xanh
A14: =PROC_TREASURY!A66 -> 46112 | B14: =PROC_TREASURY!B66 -> 50000 | C14: =PROC_TREASURY!C66 -> 2.4481096 | D14: =PROC_TREASURY!D66 -> 4.6335285 | E14: =PROC_TREASURY!E66 -> 463.35285 | F14: =PROC_TREASURY!F66 -> 926.7057 | G14: =PROC_TREASURY!H66 -> 1.8534114 | H14: =PROC_TREASURY!J66 -> Xanh
A15: =PROC_TREASURY!A67 -> 46142 | B15: =PROC_TREASURY!B67 -> 50000 | C15: =PROC_TREASURY!C67 -> 2.4499227 | D15: =PROC_TREASURY!D67 -> 4.7134511 | E15: =PROC_TREASURY!E67 -> 471.34511 | F15: =PROC_TREASURY!F67 -> 942.69022 | G15: =PROC_TREASURY!H67 -> 1.8853804 | H15: =PROC_TREASURY!J67 -> Xanh

Sheet DASH_FORECAST
A1: DASH_FORECAST - Forecast & Scenario Placeholder | B1: DASH_FORECAST - Forecast & Scenario Placeholder | C1: DASH_FORECAST - Forecast & Scenario Placeholder | D1: DASH_FORECAST - Forecast & Scenario Placeholder | E1: DASH_FORECAST - Forecast & Scenario Placeholder | F1: DASH_FORECAST - Forecast & Scenario Placeholder | G1: DASH_FORECAST - Forecast & Scenario Placeholder | H1: DASH_FORECAST - Forecast & Scenario Placeholder
A3: Forecast item | B3: Current | C3: Base forecast | D3: Upside | E3: Downside | F3: Model note
A4: USD/VND | B4: =PROC_MACRO!C67 -> 24544.076 | C4: =C4*(1+0.005) -> 0 | D4: =C4*(1-0.005) -> 0 | E4: =C4*(1+0.015) -> 0 | F4: Placeholder: replace by model output
A5: VNIBOR ON | B5: =PROC_MACRO!D67 -> 2.2684259 | C5: =C5+0.2 -> 0.2 | D5: =C5-0.3 -> -0.1 | E5: =C5+0.8 -> 1 | F5: Placeholder: replace by model output
A6: CPI | B6: =PROC_MACRO!B67 -> 5.0097812 | C6: =C6+0.1 -> 0.1 | D6: =C6-0.2 -> -0.1 | E6: =C6+0.5 -> 0.6 | F6: Placeholder: replace by model output

Sheet DASH_STRATEGY
A1: DASH_STRATEGY - Strategic Recommendations | B1: DASH_STRATEGY - Strategic Recommendations | C1: DASH_STRATEGY - Strategic Recommendations | D1: DASH_STRATEGY - Strategic Recommendations | E1: DASH_STRATEGY - Strategic Recommendations | F1: DASH_STRATEGY - Strategic Recommendations | G1: DASH_STRATEGY - Strategic Recommendations | H1: DASH_STRATEGY - Strategic Recommendations
A3: Priority | B3: Area | C3: Recommendation | D3: Owner | E3: Rationale
A4: =PROC_RECOMMENDATION!A4 -> 1 | B4: =PROC_RECOMMENDATION!B4 -> VNIBOR spike | C4: =PROC_RECOMMENDATION!C4 -> Giữ duration ngắn; hạn chế tăng vị thế bond dài hạn | D4: =PROC_RECOMMENDATION!D4 -> Treasury | E4: =PROC_RECOMMENDATION!E4 -> VNIBOR cao thường làm tăng risk premium và gây MTM loss cho duration dài.
A5: =PROC_RECOMMENDATION!A5 -> 2 | B5: =PROC_RECOMMENDATION!B5 -> FX pressure | C5: =PROC_RECOMMENDATION!C5 -> Theo dõi trạng thái USD; cân nhắc hedge/giảm trạng thái mở | D5: =PROC_RECOMMENDATION!D5 -> Treasury | E5: =PROC_RECOMMENDATION!E5 -> Biến động tỷ giá có thể ảnh hưởng thanh khoản ngoại tệ và tâm lý huy động.
A6: =PROC_RECOMMENDATION!A6 -> 3 | B6: =PROC_RECOMMENDATION!B6 -> LDR high | C6: =PROC_RECOMMENDATION!C6 -> Kiểm soát tăng trưởng tín dụng; ưu tiên huy động CASA/kỳ hạn bền vững | D6: =PROC_RECOMMENDATION!D6 -> Finance/ALM | E6: =PROC_RECOMMENDATION!E6 -> LDR cao làm giảm dư địa thanh khoản và tăng cạnh tranh huy động.
A7: =PROC_RECOMMENDATION!A7 -> 4 | B7: =PROC_RECOMMENDATION!B7 -> NPL risk | C7: =PROC_RECOMMENDATION!C7 -> Rà soát phân khúc rủi ro; tăng cảnh báo sớm tín dụng | D7: =PROC_RECOMMENDATION!D7 -> Risk/Business | E7: =PROC_RECOMMENDATION!E7 -> NPL tăng làm tăng provisioning và giảm ROA/ROE.
A8: =PROC_RECOMMENDATION!A8 -> 5 | B8: =PROC_RECOMMENDATION!B8 -> Treasury stress loss | C8: =PROC_RECOMMENDATION!C8 -> Giảm DV01 hoặc đặt stop-loss theo vốn Treasury | D8: =PROC_RECOMMENDATION!D8 -> Treasury/Risk | E8: =PROC_RECOMMENDATION!E8 -> Stress loss vượt risk appetite làm suy giảm vốn chịu rủi ro của Treasury.

Sheet CEO_BRIEF
A1: CEO Morning Brief - Auto Narrative Template | B1: CEO Morning Brief - Auto Narrative Template | C1: CEO Morning Brief - Auto Narrative Template | D1: CEO Morning Brief - Auto Narrative Template | E1: CEO Morning Brief - Auto Narrative Template | F1: CEO Morning Brief - Auto Narrative Template | G1: CEO Morning Brief - Auto Narrative Template | H1: CEO Morning Brief - Auto Narrative Template
A3: Section | B3: Auto narrative
A4: 1. Tóm tắt thị trường | B4: =TEXT(PROC_MACRO!A67,"yyyy-mm-dd")&": CPI "&TEXT(PROC_MACRO!B67,"0.00")&"%, VNIBOR ON "&TEXT(PROC_MACRO!D67,"0.00")&"%, USD/VND "&TEXT(PROC_MACRO!C67,"#,##0")&"." -> 2026-04-30: CPI 5.01%, VNIBOR ON 2.27%, USD/VND 24,544.
A5: 2. Hàm ý ngành | B5: =IF(PROC_MACRO!D67>=CONFIG!B6,"Funding cost có xu hướng chịu áp lực; ngành ngân hàng cần thận trọng với NIM và thanh khoản.","Điều kiện thanh khoản tương đối ổn định; dư địa duy trì tăng trưởng có thể tốt hơn.") -> Điều kiện thanh khoản tương đối ổn định; dư địa duy trì tăng trưởng có thể tốt hơn.
A6: 3. Hàm ý ABBank | B6: =IF(PROC_ABBANK!F67>=CONFIG!B10,"ABBank cần ưu tiên huy động bền vững/CASA và kiểm soát LDR.","ABBank có dư địa thanh khoản tương đối ổn để triển khai tăng trưởng chọn lọc.") -> ABBank cần ưu tiên huy động bền vững/CASA và kiểm soát LDR.
A7: 4. Cảnh báo chính | B7: =_xlfn.TEXTJOIN("; ",TRUE,PROC_SIGNAL!B4&": "&PROC_SIGNAL!E4,PROC_SIGNAL!B5&": "&PROC_SIGNAL!E5,PROC_SIGNAL!B6&": "&PROC_SIGNAL!E6,PROC_SIGNAL!B7&": "&PROC_SIGNAL!E7,PROC_SIGNAL!B8&": "&PROC_SIGNAL!E8) -> VNIBOR spike: Xanh; FX pressure: Xanh; LDR high: Đỏ; NPL risk: Xanh; Treasury stress loss: Xanh
A8: 5. Hành động đề xuất | B8: =_xlfn.TEXTJOIN("; ",TRUE,PROC_RECOMMENDATION!C4,PROC_RECOMMENDATION!C5,PROC_RECOMMENDATION!C6) -> Giữ duration ngắn; hạn chế tăng vị thế bond dài hạn; Theo dõi trạng thái USD; cân nhắc hedge/giảm trạng thái mở; Kiểm soát tăng trưởng tín dụng; ưu tiên huy động CASA/kỳ hạn bền vững

Sheet FORECAST_HISTORY
A1: FORECAST_HISTORY - Model Output Log | B1: FORECAST_HISTORY - Model Output Log | C1: FORECAST_HISTORY - Model Output Log | D1: FORECAST_HISTORY - Model Output Log | E1: FORECAST_HISTORY - Model Output Log | F1: FORECAST_HISTORY - Model Output Log | G1: FORECAST_HISTORY - Model Output Log | H1: FORECAST_HISTORY - Model Output Log | I1: FORECAST_HISTORY - Model Output Log
A3: run_date | B3: forecast_date | C3: variable | D3: model | E3: forecast | F3: lower_band | G3: upper_band | H3: actual | I3: error

Sheet ALERT_LOG
A1: ALERT_LOG - Breach & Watch Log | B1: ALERT_LOG - Breach & Watch Log | C1: ALERT_LOG - Breach & Watch Log | D1: ALERT_LOG - Breach & Watch Log | E1: ALERT_LOG - Breach & Watch Log | F1: ALERT_LOG - Breach & Watch Log | G1: ALERT_LOG - Breach & Watch Log
A3: date | B3: signal | C3: level | D3: metric_value | E3: action_taken | F3: owner | G3: status
